Workbook

Sheet project
A1: Project_Id | B1: Project | C1: Estimate | D1: Start | E1: Signed_On | F1: Due_Date | G1: Duration | H1: Archived | I1: Archived_Date | J1: Probability | K1: Client_PO | L1: Job_Order | M1: PM | N1: Account | O1: Job_Order_Category | P1: Is_Progress_Percent | Q1: Project_Type | R1: Client | S1: Client_Contact | T1: Program_Charter | U1: Business_Unit | V1: Stage | W1: Suggested_Price | X1: External_Cost | Y1: Internal_Cost | Z1: Travel_Cost | AA1: Expense_Cost | AB1: Progress % | AC1: Budget Consumption % | AD1: Worked hours value | AE1: Invoiced | AF1: Ordered | AG1: Travels | AH1: Expenses | AI1: Internal Cost (Projected) | AJ1: Gross Margin (Last Budget Version) | AK1: Gross Margin % (Last Budget Version) | AL1: Gross Margin (Projected) | AM1: Gross Margin % (Projected) | AN1: Contribution Margin (Last Budget Version) | AO1: Contribution Margin % (Last Budget Version) | AP1: Contribution Margin (Projected) | AQ1: Contribution Margin % (Projected) | AR1: Data chiusura | AS1: Data apertura | AT1: Committente | AU1: Settore | AV1: Finanziato SI/NO | AW1: RIFATTURAZIONE | AX1: Sales Type | AY1: Paesi | AZ1: Intrarea | BA1: Sales 2 | BB1: Numero preventivo
A2: 7 | B2: BOSCAROL SRL_2020 | C2: 11000 | D2: 43831 | G2: 12 | H2: yes | I2: 44596 | J2: 100 | L2: 20B101 | M2: Gaia Seghezzi | N2: Gaia Seghezzi | O2: cliente | Q2: OLD_Temporary Export Management | R2: BOSCAROL SRL | U2: Business Expander | V2: Won | W2: 12000 | Y2: 3840 | AB2: 100 | AC2: 31.56 | AD2: 1212 | AI2: 1212 | AJ2: 11000 | AK2: 100 | AL2: 11000 | AM2: 100 | AN2: 7160 | AO2: 65.090909 | AP2: 9788 | AQ2: 88.981818 | AV2: NO | AX2: SI
A3: 11 | B3: LUCANA SALUMI | C3: 24500 | D3: 44075 | G3: 4 | H3: yes | I3: 44497 | M3: Alessandra Garlini | N3: Alessandra Garlini | O3: cliente | Q3: OLD_Temporary Export Management | R3: Lucana Salumi | U3: Business Expander | V3: Lost | W3: 12250 | X3: 12250 | AJ3: 12250 | AK3: 50 | AL3: 12250 | AM3: 50 | AN3: 12250 | AO3: 50 | AP3: 12250 | AQ3: 50 | AV3: SI | AX3: SI
A4: 12 | B4: Minonzio | C4: 12000 | D4: 43831 | G4: 12 | H4: yes | I4: 44596 | J4: 100 | L4: 20B103 | M4: Alessandra Garlini | N4: Alessandra Garlini | O4: cliente | Q4: OLD_Temporary Export Management | R4: Minonzio Srl | U4: Business Expander | V4: Won | W4: 10400 | Y4: 3648 | AB4: 100 | AC4: 59.38 | AD4: 2964 | AI4: 2964 | AJ4: 12000 | AK4: 100 | AL4: 12000 | AM4: 100 | AN4: 8352 | AO4: 69.6 | AP4: 9036 | AQ4: 75.3 | AV4: NO | AX4: NO
A5: 13 | B5: NTS BE 2020 | C5: 8800 | D5: 43831 | G5: 6 | H5: yes | I5: 44595 | J5: 100 | L5: 19B019 | M5: Francesca Poletti | N5: Giovanna Ricuperati | O5: cliente | Q5: OLD_Temporary Export Management | R5: NTS Spa | U5: Business Expander | V5: Won | W5: 6000 | Y5: 1600 | AB5: 100 | AC5: 41.25 | AD5: 728 | AI5: 728 | AJ5: 8800 | AK5: 100 | AL5: 8800 | AM5: 100 | AN5: 7200 | AO5: 81.818182 | AP5: 8072 | AQ5: 91.727273 | AV5: NO | AX5: SI
A6: 14 | B6: Olio Masturzo_TEM | C6: 8000 | D6: 43831 | G6: 4 | H6: yes | I6: 44596 | J6: 100 | L6: 19B020 | M6: Annalisa Surini | N6: Alessandra Garlini | O6: cliente | Q6: OLD_Temporary Export Management | R6: Oleifici Fratelli Masturzo Snc | U6: Business Expander | V6: Won | W6: 6800 | X6: 800 | Y6: 1920 | AB6: 100 | AC6: 13.75 | AD6: 290 | AI6: 290 | AJ6: 7200 | AK6: 90 | AL6: 8000 | AM6: 100 | AN6: 5280 | AO6: 66 | AP6: 7710 | AQ6: 96.375 | AU6: Food | AV6: SI | AX6: NO | AY6: DACH
A7: 15 | B7: Pirola BE 2020 | C7: 2000 | D7: 43831 | G7: 2 | H7: yes | I7: 44595 | J7: 100 | L7: 19B022 | M7: Francesca Poletti | N7: Alessandra Garlini | O7: cliente | Q7: OLD_Temporary Export Management | R7: Pirola | U7: Business Expander | V7: Won | W7: 2400 | Y7: 640 | AB7: 100 | AJ7: 2000 | AK7: 100 | AL7: 2000 | AM7: 100 | AN7: 1360 | AO7: 68 | AP7: 2000 | AQ7: 100 | AV7: NO | AX7: NO
A8: 16 | B8: SULZER | C8: 28000 | D8: 44013 | G8: 6 | H8: yes | I8: 44497 | M8: Alessandra Garlini | N8: Alessandra Garlini | O8: cliente | Q8: OLD_Temporary Export Management | R8: SULZER SRL | U8: Business Expander | V8: Lost | AJ8: 28000 | AK8: 100 | AL8: 28000 | AM8: 100 | AN8: 28000 | AO8: 100 | AP8: 28000 | AQ8: 100 | AV8: SI | AX8: NO
A9: 17 | B9: Tornilastra | C9: 14000 | D9: 43831 | G9: 12 | H9: yes | I9: 44596 | J9: 100 | L9: 20B106 | M9: Alessandra Garlini | N9: Alessandra Garlini | O9: cliente | Q9: OLD_Temporary Export Management | R9: Tornilastra Srl | U9: Business Expander | V9: Won | W9: 19200 | Y9: 7104 | AB9: 100 | AC9: 2.86 | AD9: 203.5 | AI9: 203.5 | AJ9: 14000 | AK9: 100 | AL9: 14000 | AM9: 100 | AN9: 6896 | AO9: 49.257143 | AP9: 13796.5 | AQ9: 98.546429 | AV9: NO | AX9: SI
A10: 18 | B10: Graziani 2020 | C10: 10000 | D10: 43831 | G10: 12 | H10: yes | I10: 44596 | J10: 100 | L10: 19B046 | M10: Gaia Seghezzi | N10: Claudia Nikolai | O10: cliente | Q10: OLD_Temporary Export Management | R10: Officina Graziani Srl | U10: Business Expander | V10: Won | W10: 7200 | Y10: 2304 | AB10: 100 | AC10: 126.04 | AD10: 2904 | AI10: 2904 | AJ10: 10000 | AK10: 100 | AL10: 10000 | AM10: 100 | AN10: 7696 | AO10: 76.96 | AP10: 7096 | AQ10: 70.96 | AU10: Meccanica | AV10: NO | AX10: SI
A11: 19 | B11: AAB_OMCS PLAST_2020 | C11: 19800 | D11: 43831 | G11: 12 | H11: yes | I11: 44596 | J11: 100 | L11: 20B102 | M11: Alessandra Garlini | N11: Gaia Seghezzi | O11: cliente | Q11: OLD_Temporary Export Management | R11: OMCS PLAST SRL | T11: Associazione Artigiani | U11: Business Expander | V11: Won | W11: 19200 | Y11: 7104 | AB11: 100 | AC11: 134.64 | AD11: 9564.5 | AI11: 9564.5 | AJ11: 19800 | AK11: 100 | AL11: 19800 | AM11: 100 | AN11: 12696 | AO11: 64.121212 | AP11: 10235.5 | AQ11: 51.694444 | AT11: ASSOART | AU11: Gomma e plastica | AV11: NO | AX11: SI | AY11: Europa
A12: 20 | B12: Progtech | C12: 15000 | D12: 43983 | G12: 8 | H12: yes | I12: 44497 | M12: Cristian Pellegrini | N12: Alessandra Garlini | O12: cliente | Q12: OLD_Temporary Export Management | R12: Progtech srl | U12: Business Expander | V12: Lost | AJ12: 15000 | AK12: 100 | AL12: 15000 | AM12: 100 | AN12: 15000 | AO12: 100 | AP12: 15000 | AQ12: 100 | AV12: NO | AX12: NO
A13: 21 | B13: APA MONZA_TEKNOFLUOR SR_2020 | C13: 6300 | D13: 43831 | G13: 7 | H13: yes | I13: 44596 | J13: 100 | L13: 20B109 | M13: Elena Barcella | N13: Alessandra Garlini | O13: cliente | Q13: Sales Expander | R13: Teknofluor Srl | T13: Associazione Artigiani | U13: Business Expander | V13: Won | W13: 5600 | Y13: 1792 | AB13: 100 | AC13: 36.16 | AD13: 660 | AI13: 660 | AJ13: 6300 | AK13: 100 | AL13: 6300 | AM13: 100 | AN13: 4508 | AO13: 71.555556 | AP13: 5640 | AQ13: 89.52381 | AT13: APA MONZA | AV13: NO | AX13: SI
A14: 22 | B14: AAB_FERRARI DIONIGI_19/20 | C14: 4500 | D14: 43831 | G14: 6 | H14: yes | I14: 44595 | J14: 100 | L14: 19B034 | M14: Annalisa Surini | N14: Gaia Seghezzi | O14: cliente | Q14: Sales Expander | R14: FERRARI DIONIGI Srl | T14: Associazione Artigiani | U14: Business Expander | V14: Won | W14: 6000 | Y14: 1920 | AB14: 100 | AC14: 30 | AD14: 589 | AI14: 589 | AJ14: 4500 | AK14: 100 | AL14: 4500 | AM14: 100 | AN14: 2580 | AO14: 57.333333 | AP14: 3911 | AQ14: 86.911111 | AT14: ASSOART | AU14: Meccanica | AV14: NO | AX14: SI | AY14: Italia
A15: 23 | B15: AAB_FORMENTI SRL_20SE | C15: 4050 | D15: 43831 | G15: 5 | H15: yes | I15: 44596 | J15: 100 | L15: 19B035 | M15: Annalisa Surini | N15: Gaia Seghezzi | O15: cliente | Q15: Sales Expander | R15: Formenti Srl | T15: Associazione Artigiani | U15: Business Expander | V15: Won | W15: 4800 | Y15: 1536 | AB15: 100 | AJ15: 4050 | AK15: 100 | AL15: 4050 | AM15: 100 | AN15: 2514 | AO15: 62.074074 | AP15: 4050 | AQ15: 100 | AT15: ASSOART | AU15: Meccanica | AV15: NO | AX15: NO
A16: 24 | B16: AAB_FRATUS SRL | C16: 4725 | D16: 43831 | G16: 4 | H16: yes | I16: 44596 | J16: 100 | L16: 19B037 | M16: Gaia Seghezzi | N16: Gaia Seghezzi | O16: cliente | Q16: Sales Expander | R16: FRATUS Srl | T16: Associazione Artigiani | U16: Business Expander | V16: Won | W16: 4800 | Y16: 1536 | AB16: 100 | AC16: 59.38 | AD16: 912 | AI16: 912 | AJ16: 4725 | AK16: 100 | AL16: 4725 | AM16: 100 | AN16: 3189 | AO16: 67.492063 | AP16: 3813 | AQ16: 80.698413 | AT16: ASSOART | AU16: Gomma e plastica | AV16: NO | AX16: SI
A17: 25 | B17: AAB_OFFICINA MECCANICA RINALDI | C17: 12870 | D17: 43891 | G17: 13 | H17: yes | I17: 44601 | J17: 100 | L17: 20B111 | M17: Valentina Premoli | N17: Gaia Seghezzi | O17: cliente | Q17: Sales Expander | R17: Officina Meccanica Rinaldi Snc | T17: Associazione Artigiani | U17: Business Expander | V17: Won | W17: 10400 | Y17: 3328 | AB17: 100 | AC17: 57.45 | AD17: 1954 | AI17: 1954 | AJ17: 12870 | AK17: 100 | AL17: 12870 | AM17: 100 | AN17: 9542 | AO17: 74.141414 | AP17: 10916 | AQ17: 84.817405 | AT17: ASSOART | AU17: Meccanica | AV17: NO | AX17: NO | AY17: Europa
A18: 26 | B18: AAB_PROJECT PACKAGING_2020 | C18: 12150 | D18: 43831 | G18: 12 | H18: yes | I18: 44596 | J18: 100 | L18: 20B114 | M18: Elena Barcella | N18: Gaia Seghezzi | O18: cliente | Q18: Sales Expander | R18: Project Packaging Srl | T18: Associazione Artigiani | U18: Business Expander | V18: Won | W18: 9600 | Y18: 3072 | AB18: 100 | AC18: 66.15 | AD18: 2221 | AI18: 2221 | AJ18: 12150 | AK18: 100 | AL18: 12150 | AM18: 100 | AN18: 9078 | AO18: 74.716049 | AP18: 9929 | AQ18: 81.720165 | AT18: ASSOART | AU18: Gomma e plastica | AV18: NO | AX18: SI | AY18: Italia
A19: 27 | B19: AAB_RCL DOMINO_2020 | C19: 15086 | D19: 43831 | G19: 12 | H19: yes | I19: 44596 | J19: 100 | L19: 20B110 | M19: Gaia Seghezzi | N19: Gaia Seghezzi | O19: cliente | Q19: Sales Expander | R19: RCL DOMINO Srl | T19: Associazione Artigiani | U19: Business Expander | V19: Won | W19: 14400 | Y19: 4608 | AB19: 100 | AC19: 60.16 | AD19: 2760 | AI19: 2760 | AJ19: 15086 | AK19: 100 | AL19: 15086 | AM19: 100 | AN19: 10478 | AO19: 69.455124 | AP19: 12326 | AQ19: 81.704892 | AT19: ASSOART | AV19: NO | AX19: SI
A20: 28 | B20: AAB_SPINI UOVA_CR | C20: 15000 | D20: 43983 | G20: 12 | H20: yes | I20: 45184 | M20: Valentina Premoli | N20: Gaia Seghezzi | O20: cliente | Q20: Sales Expander | R20: Spini Uova | T20: Associazione Artigiani | U20: Business Expander | V20: Lost | AJ20: 15000 | AK20: 100 | AL20: 15000 | AM20: 100 | AN20: 15000 | AO20: 100 | AP20: 15000 | AQ20: 100 | AT20: ASSOART | AV20: NO | AX20: SI
A21: 29 | B21: AAB_TOP QUALITY | C21: 3240 | D21: 43831 | G21: 3 | H21: yes | I21: 44596 | J21: 100 | L21: 19B043 | M21: Gaia Seghezzi | N21: Gaia Seghezzi | O21: cliente | Q21: Sales Expander | R21: TOP QUALITY Srl | T21: Associazione Artigiani | U21: Business Expander | V21: Won | W21: 6000 | Y21: 1920 | AB21: 100 | AC21: 5.63 | AD21: 108 | AI21: 108 | AJ21: 3240 | AK21: 100 | AL21: 3240 | AM21: 100 | AN21: 1320 | AO21: 40.740741 | AP21: 3132 | AQ21: 96.666667 | AT21: ASSOART | AV21: SI | AX21: SI
A22: 30 | B22: AAB_VALTORTA SRL | C22: 1260 | D22: 43831 | G22: 1 | H22: yes | I22: 44601 | J22: 100 | L22: 19B044 | M22: Valentina Premoli | N22: Gaia Seghezzi | O22: cliente | Q22: Sales Expander | R22: VALTORTA Srl | T22: Associazione Artigiani | U22: Business Expander | V22: Won | W22: 800 | Y22: 256 | AB22: 100 | AJ22: 1260 | AK22: 100 | AL22: 1260 | AM22: 100 | AN22: 1004 | AO22: 79.68254 | AP22: 1260 | AQ22: 100 | AT22: ASSOART | AU22: Meccanica | AV22: NO | AX22: NO
A23: 31 | B23: AAB_LANZENI MARIO_20 | C23: 3240 | D23: 44075 | G23: 3 | H23: yes | I23: 44596 | J23: 100 | L23: 20B132 | M23: Annalisa Surini | N23: Gaia Seghezzi | O23: cliente | Q23: Sales Expander | R23: LANZENI MARIO Srl | T23: Associazione Artigiani | U23: Business Expander | V23: Won | W23: 3600 | Y23: 1152 | AB23: 100 | AC23: 160.42 | AD23: 1560 | AI23: 1560 | AJ23: 3240 | AK23: 100 | AL23: 3240 | AM23: 100 | AN23: 2088 | AO23: 64.444444 | AP23: 1680 | AQ23: 51.851852 | AT23: ASSOART | AU23: Arredamento | AV23: SI | AX23: SI | AY23: Italia
A24: 32 | B24: AAB_SD Laser | C24: 2925 | D24: 43831 | G24: 4 | H24: yes | I24: 44596 | J24: 100 | L24: 19B045 | M24: Elena Barcella | N24: Gaia Seghezzi | O24: cliente | Q24: Sales Expander | R24: SD Laser | T24: Associazione Artigiani | U24: Business Expander | V24: Won | W24: 3200 | Y24: 1024 | AB24: 100 | AJ24: 2925 | AK24: 100 | AL24: 2925 | AM24: 100 | AN24: 1901 | AO24: 64.991453 | AP24: 2925 | AQ24: 100 | AT24: ASSOART | AV24: NO | AX24: SI
A25: 33 | B25: AAB_KRONOS SRL | C25: 12150 | D25: 43862 | G25: 12 | H25: yes | I25: 44601 | J25: 100 | L25: 20B116 | M25: Valentina Premoli | N25: Gaia Seghezzi | O25: cliente | Q25: Sales Expander | R25: Kronos Srl | T25: Associazione Artigiani | U25: Business Expander | V25: Won | W25: 9600 | Y25: 3072 | AB25: 100 | AC25: 62.76 | AD25: 1991 | AI25: 1991 | AJ25: 12150 | AK25: 100 | AL25: 12150 | AM25: 100 | AN25: 9078 | AO25: 74.716049 | AP25: 10159 | AQ25: 83.613169 | AT25: ASSOART | AU25: Altro | AV25: NO | AX25: SI | AY25: Mondo
A26: 34 | B26: AAB_TOP QUALITY_2020/21 | C26: 9900 | D26: 44013 | G26: 8 | H26: yes | I26: 44596 | J26: 100 | L26: 20B146 | M26: Gaia Seghezzi | N26: Gaia Seghezzi | O26: cliente | Q26: Sales Expander | R26: TOP QUALITY Srl | T26: Associazione Artigiani | U26: Business Expander | V26: Won | W26: 9600 | Y26: 3072 | AB26: 100 | AC26: 100.39 | AD26: 2636 | AI26: 2636 | AJ26: 9900 | AK26: 100 | AL26: 9900 | AM26: 100 | AN26: 6828 | AO26: 68.969697 | AP26: 7264 | AQ26: 73.373737 | AT26: ASSOART | AU26: Meccanica | AV26: SI | AX26: SI | AY26: Europa
A27: 35 | B27: AAB_FRATUS SRL_2020/21 | C27: 11756 | D27: 43983 | G27: 9 | H27: yes | I27: 44596 | J27: 100 | L27: 20B127 | M27: Gaia Seghezzi | N27: Gaia Seghezzi | O27: cliente | Q27: Sales Expander | R27: FRATUS Srl | T27: Associazione Artigiani | U27: Business Expander | V27: Won | W27: 11400 | Y27: 3648 | AB27: 100 | AC27: 66.45 | AD27: 2008 | AI27: 2008 | AJ27: 11756 | AK27: 100 | AL27: 11756 | AM27: 100 | AN27: 8108 | AO27: 68.969037 | AP27: 9748 | AQ27: 82.91936 | AT27: ASSOART | AU27: Gomma e plastica | AV27: NO | AX27: SI | AY27: Europa
A28: 37 | B28: AAB_EREDI PIANA_2020 | C28: 12870 | D28: 43862 | G28: 13 | H28: yes | I28: 44601 | J28: 100 | L28: 20B115 | M28: Valentina Premoli | N28: Gaia Seghezzi | O28: cliente | Q28: Sales Expander | R28: Verniciature industriali Eredi Piana S.N.C di Piana Carlo E C. | T28: Associazione Artigiani | U28: Business Expander | V28: Won | W28: 9600 | Y28: 3072 | AB28: 100 | AC28: 53.39 | AD28: 1661 | AI28: 1661 | AJ28: 12870 | AK28: 100 | AL28: 12870 | AM28: 100 | AN28: 9798 | AO28: 76.130536 | AP28: 11209 | AQ28: 87.094017 | AT28: ASSOART | AU28: Meccanica | AV28: NO | AX28: NO | AY28: Italia
A29: 38 | B29: AAB_FERRARI DIONIGI_20/21 | C29: 12150 | D29: 44013 | G29: 12 | H29: yes | I29: 44596 | J29: 100 | L29: 20B144 | M29: Annalisa Surini | N29: Gaia Seghezzi | O29: cliente | Q29: Sales Expander | R29: FERRARI DIONIGI Srl | S29: Francesca Ferrari | T29: Associazione Artigiani | U29: Business Expander | V29: Won | W29: 14700 | Y29: 4704 | AB29: 100 | AC29: 80.48 | AD29: 3406 | AI29: 3406 | AJ29: 12150 | AK29: 100 | AL29: 12150 | AM29: 100 | AN29: 7446 | AO29: 61.283951 | AP29: 8744 | AQ29: 71.967078 | AT29: ASSOART | AU29: Meccanica | AV29: NO | AX29: SI | AY29: Italia
A30: 39 | B30: AAB_FORMENTI SRL_20/21SE | C30: 12150 | D30: 43952 | G30: 12 | H30: yes | I30: 44596 | J30: 100 | L30: 20B128 | M30: Annalisa Surini | N30: Gaia Seghezzi | O30: cliente | Q30: Sales Expander | R30: Formenti Srl | T30: Associazione Artigiani | U30: Business Expander | V30: Won | W30: 14400 | Y30: 4608 | AB30: 100 | AC30: 76.56 | AD30: 3509 | AI30: 3509 | AJ30: 12150 | AK30: 100 | AL30: 12150 | AM30: 100 | AN30: 7542 | AO30: 62.074074 | AP30: 8641 | AQ30: 71.119342 | AT30: ASSOART | AU30: Meccanica | AV30: SI | AX30: SI | AY30: Italia
A31: 40 | B31: AAB_Falegnameria Vitali_2020 | C31: 14850 | D31: 43862 | G31: 12 | H31: yes | I31: 44596 | J31: 100 | L31: 20B117 | M31: Elena Barcella | N31: Gaia Seghezzi | O31: cliente | Q31: Sales Expander | R31: FALEGNAMERIA VITALI FEDERICO DI FAUSTO ED EUGENIO VITALI S.N.C. | T31: Associazione Artigiani | U31: Business Expander | V31: Won | W31: 9600 | Y31: 3072 | AB31: 100 | AC31: 96.09 | AD31: 2994 | AI31: 2994 | AJ31: 14850 | AK31: 100 | AL31: 14850 | AM31: 100 | AN31: 11778 | AO31: 79.313131 | AP31: 11856 | AQ31: 79.838384 | AT31: ASSOART | AU31: Arredamento | AV31: SI | AX31: SI | AY31: Europa
A32: 41 | B32: APA MONZA_Eredi Boffi | C32: 7200 | D32: 43922 | G32: 7 | H32: yes | I32: 44601 | J32: 100 | L32: 20B123 | M32: Valentina Premoli | N32: Gaia Seghezzi | O32: cliente | Q32: Sales Expander | R32: Eredi Di Boffi Mario di Boffi Elio srl | T32: Associazione Artigiani | U32: Business Expander | V32: Won | W32: 7200 | Y32: 2384 | AB32: 100 | AC32: 71.09 | AD32: 1603 | AI32: 1603 | AJ32: 7200 | AK32: 100 | AL32: 7200 | AM32: 100 | AN32: 4816 | AO32: 66.888889 | AP32: 5597 | AQ32: 77.736111 | AT32: APA MONZA | AU32: Meccanica | AV32: NO | AX32: NO
A33: 42 | B33: AAB_OMCF 2020 | C33: 15570 | D33: 43862 | G33: 13 | H33: yes | I33: 44596 | J33: 100 | L33: 20B122 | M33: Elena Barcella | N33: Gaia Seghezzi | O33: cliente | Q33: Sales Expander | R33: OMCF Lavorazioni Meccaniche Srl | T33: Associazione Artigiani | U33: Business Expander | V33: Won | W33: 15200 | Y33: 5064 | AB33: 100 | AC33: 64.2 | AD33: 2796 | AI33: 2796 | AJ33: 15570 | AK33: 100 | AL33: 15570 | AM33: 100 | AN33: 10506 | AO33: 67.475915 | AP33: 12774 | AQ33: 82.042389 | AT33: ASSOART | AU33: Meccanica | AV33: NO | AX33: NO | AY33: Italia
A34: 43 | B34: Blu Elettro | C34: 8000 | D34: 43983 | G34: 6 | H34: yes | I34: 44601 | J34: 100 | M34: Valentina Premoli | N34: Giovanna Ricuperati | O34: cliente | Q34: Sales Expander | R34: Blu Elettro srl | U34: Business Expander | V34: Won | W34: 7200 | Y34: 1920 | AB34: 100 | AC34: 109.9 | AD34: 2045 | AI34: 2045 | AJ34: 8000 | AK34: 100 | AL34: 8000 | AM34: 100 | AN34: 6080 | AO34: 76 | AP34: 5955 | AQ34: 74.4375 | AT34: CNA | AU34: Meccanica | AV34: NO | AX34: NO
A35: 44 | B35: Agla Elettronica BE 2020 | C35: 35000 | D35: 43831 | G35: 15 | H35: yes | I35: 44595 | J35: 100 | L35: 20X106 | M35: Francesca Poletti | N35: Alessandra Garlini | O35: cliente | R35: AGLA Elettronica Srl | U35: Business Expander | V35: Won | W35: 21000 | Y35: 5600 | AB35: 100 | AC35: 56.34 | AD35: 3244.25 | AI35: 3244.25 | AJ35: 35000 | AK35: 100 | AL35: 35000 | AM35: 100 | AN35: 29400 | AO35: 84 | AP35: 31755.75 | AQ35: 90.730714 | AU35: Elettrico/Elettronico | AV35: SI | AX35: SI | AY35: Europa | AZ35: BE-COM
A36: 45 | B36: Trixia Sviluppo Pagode | C36: 3250 | D36: 43891 | G36: 4 | H36: yes | I36: 44621 | J36: 100 | L36: 20X107 | M36: Valentina Bucca | N36: Giovanna Ricuperati | O36: cliente | R36: Trixia Srl - Avalon | S36: d s | U36: Business Expander | V36: Won | W36: 10400 | Y36: 3328 | AB36: 100 | AC36: 65.34 | AD36: 1944 | AI36: 1944 | AJ36: 3250 | AK36: 100 | AL36: 3250 | AM36: 100 | AN36: -78 | AO36: -2.4 | AP36: 1306 | AQ36: 40.184615 | AU36: Edilizia | AV36: NO | AX36: NO
A37: 46 | B37: Calvi marketing 2020 | C37: 90000 | D37: 43831 | G37: 6 | H37: yes | I37: 44621 | J37: 100 | L37: 19B005 | M37: Valentina Bucca | N37: Giovanna Ricuperati | O37: cliente | Q37: Temporary Marketing Management | R37: Calvi Holding s.r.l | U37: Business Expander | V37: Won | W37: 50000 | Y37: 16800 | AB37: 100 | AC37: 10.47 | AD37: 2037 | AI37: 2037 | AJ37: 90000 | AK37: 100 | AL37: 90000 | AM37: 100 | AN37: 73200 | AO37: 81.333333 | AP37: 87963 | AQ37: 97.736667 | AU37: Altro | AV37: NO | AX37: SI
A38: 47 | B38: Affiancamento Calvi Spa | C38: 15000 | D38: 43831 | G38: 12 | H38: yes | I38: 44621 | J38: 100 | L38: 19B006 | M38: Valentina Bucca | N38: Giovanna Ricuperati | O38: cliente | Q38: Temporary Marketing Management | R38: CALVI S.P.A. | U38: Business Expander | V38: Won | W38: 14400 | Y38: 4608 | AB38: 100 | AC38: 7.03 | AD38: 324 | AI38: 324 | AJ38: 15000 | AK38: 100 | AL38: 15000 | AM38: 100 | AN38: 10392 | AO38: 69.28 | AP38: 14676 | AQ38: 97.84 | AU38: Altro | AV38: NO | AX38: SI
A39: 48 | B39: Fimer- ABB | C39: 38000 | D39: 43831 | G39: 4 | H39: yes | I39: 44621 | J39: 100 | L39: 20B108 | M39: Valentina Bucca | N39: Giovanna Ricuperati | O39: cliente | Q39: Assessment | R39: Fimer spa | U39: Business Expander | V39: Won | W39: 32200 | X39: 15000 | Y39: 5824 | AB39: 100 | AF39: 15000 | AJ39: 23000 | AK39: 60.526316 | AL39: 23000 | AM39: 60.526316 | AN39: 17176 | AO39: 45.2 | AP39: 23000 | AQ39: 60.526316 | AU39: Impianti | AV39: NO | AX39: NO
A40: 49 | B40: Assessment Magnetti | C40: 25000 | D40: 44197 | G40: 4 | H40: yes | I40: 44497 | L40: 20B119 | M40: Francesca Gritti | N40: Giovanna Ricuperati | O40: cliente | Q40: Assessment | R40: Magnetti Building spa | U40: Business Expander | V40: Lost | W40: 22600 | Y40: 7032 | AB40: 100 | AC40: 0.89 | AD40: 111 | AI40: 111 | AJ40: 25000 | AK40: 100 | AL40: 25000 | AM40: 100 | AN40: 17968 | AO40: 71.872 | AP40: 24889 | AQ40: 99.556 | AV40: NO | AX40: NO
A41: 50 | B41: Mascagni Casa | C41: 5000 | D41: 43831 | G41: 11 | H41: yes | I41: 44601 | J41: 100 | L41: 19B032 | M41: Federica Perico | N41: Claudia Nikolai | O41: cliente | Q41: OLD_Lead Generation | R41: Mascagni Casa | U41: Business Expander | V41: Won | W41: 6000 | Y41: 1920 | AB41: 100 | AC41: 73.75 | AD41: 1422.5 | AI41: 1422.5 | AJ41: 5000 | AK41: 100 | AL41: 5000 | AM41: 100 | AN41: 3080 | AO41: 61.6 | AP41: 3577.5 | AQ41: 71.55 | AU41: Accessori casa | AV41: SI | AX41: NO
A42: 51 | B42: Marketest Gomma | C42: 5000 | D42: 43983 | G42: 2 | H42: yes | I42: 44621 | J42: 100 | L42: 19B012 | M42: Valentina Bucca | N42: Giovanna Ricuperati | O42: cliente | Q42: Ricerca di Mercato | R42: Lombardia Fiere | U42: Business Expander | V42: Won | W42: 4800 | Y42: 1536 | AB42: 100 | AC42: 56.25 | AD42: 1080 | AI42: 1080 | AJ42: 5000 | AK42: 100 | AL42: 5000 | AM42: 100 | AN42: 3464 | AO42: 69.28 | AP42: 3920 | AQ42: 78.4 | AU42: Altro | AV42: NO | AX42: SI
A43: 52 | B43: Cosmetica italia_bandi 2020 | C43: 7800 | D43: 43831 | G43: 12 | H43: yes | I43: 44601 | J43: 100 | L43: 19B030 | M43: Valentina Premoli | N43: Claudia Nikolai | O43: cliente | Q43: Ricerca di Mercato | R43: Cosmetica Italia | U43: FINC | V43: Won | W43: 4800 | Y43: 1536 | AB43: 100 | AC43: 25 | AD43: 430 | AI43: 430 | AJ43: 7800 | AK43: 100 | AL43: 7800 | AM43: 100 | AN43: 6264 | AO43: 80.307692 | AP43: 7370 | AQ43: 94.487179 | AU43: Cosmetica | AV43: NO | AX43: SI
A44: 53 | B44: Cosmetica italia ricerca | C44: 7000 | D44: 43831 | G44: 2 | H44: yes | I44: 44596 | J44: 100 | L44: 19B031 | M44: Francesca Gritti | N44: Claudia Nikolai | O44: cliente | Q44: Ricerca di Mercato | R44: Cosmetica Italia | U44: Business Expander | V44: Won | W44: 8000 | Y44: 2344 | AB44: 100 | AJ44: 7000 | AK44: 100 | AL44: 7000 | AM44: 100 | AN44: 4656 | AO44: 66.514286 | AP44: 7000 | AQ44: 100 | AU44: Cosmetica | AV44: NO | AX44: SI
A45: 54 | B45: Rational production | C45: 4000 | D45: 43831 | G45: 3 | H45: yes | I45: 44621 | J45: 100 | L45: 20B104 | M45: Valentina Bucca | N45: Giovanna Ricuperati | O45: cliente | Q45: Ricerca di Mercato | R45: Rational production srl | U45: Business Expander | V45: Won | W45: 5000 | Y45: 1600 | AB45: 100 | AC45: 29.38 | AD45: 531.5 | AI45: 531.5 | AJ45: 4000 | AK45: 100 | AL45: 4000 | AM45: 100 | AN45: 2400 | AO45: 60 | AP45: 3468.5 | AQ45: 86.7125 | AU45: Altro | AV45: NO | AX45: SI
A46: 55 | B46: Pedrini Ricerca | C46: 6400 | D46: 43922 | G46: 1 | H46: yes | I46: 44859 | J46: 100 | L46: 20B126 | M46: Cristian Pellegrini | N46: Giovanna Ricuperati | O46: cliente | Q46: Ricerca di Mercato | R46: Pedrini Spa | U46: Business Expander | V46: Won | W46: 3800 | X46: 1400 | Y46: 776 | AB46: 100 | AF46: 1400 | AJ46: 5000 | AK46: 78.125 | AL46: 5000 | AM46: 78.125 | AN46: 4224 | AO46: 66 | AP46: 5000 | AQ46: 78.125 | AV46: NO | AX46: SI
A47: 56 | B47: Mabo | C47: 750 | D47: 43831 | G47: 2 | H47: yes | I47: 44497 | L47: 19B015 | M47: Francesca Poletti | N47: Giovanna Ricuperati | O47: cliente | Q47: Assessment | R47: Mabo S.pa. | U47: Business Expander | V47: Lost | AD47: 37 | AJ47: 750 | AK47: 100 | AL47: 750 | AM47: 100 | AN47: 750 | AO47: 100 | AP47: 750 | AQ47: 100 | AV47: NO | AX47: NO
A48: 57 | B48: Coop Serena | C48: 18000 | D48: 43862 | G48: 5 | H48: yes | I48: 44621 | J48: 100 | L48: 20B118 | M48: Valentina Bucca | N48: Giovanna Ricuperati | O48: cliente | Q48: Assessment | R48: Cooperativa Serena | U48: Business Expander | V48: Won | W48: 17800 | Y48: 5856 | AB48: 100 | AC48: 123.71 | AD48: 6893 | AI48: 6893 | AJ48: 18000 | AK48: 100 | AL48: 18000 | AM48: 100 | AN48: 12144 | AO48: 67.466667 | AP48: 11107 | AQ48: 61.705556 | AU48: Altro | AV48: NO | AX48: NO
A49: 58 | B49: Wenda rifatturazione Inn. manager | C49: 53440 | D49: 44136 | G49: 9 | H49: yes | I49: 44628 | J49: 100 | L49: 20X126 | M49: Claudia Nikolai | N49: Claudia Nikolai | O49: cliente | Q49: Social Media Management | R49: Wenda | U49: Comunicazione | V49: Won | W49: 53440 | X49: 53440 | AU49: IT | AV49: SI | AX49: NO
A50: 59 | B50: AAB_MARTOCCIA MOOD | C50: 2000 | D50: 44287 | G50: 1 | H50: yes | I50: 45184 | M50: Elena Barcella | N50: Gaia Seghezzi | O50: cliente | Q50: Sales Expander | R50: Martoccia Mood srl | T50: Associazione Artigiani | U50: Business Expander | V50: Lost | AJ50: 2000 | AK50: 100 | AL50: 2000 | AM50: 100 | AN50: 2000 | AO50: 100 | AP50: 2000 | AQ50: 100 | AT50: ASSOART | AV50: NO | AX50: SI
A51: 60 | B51: AAB_FLLI SALANTI_CR | C51: 8000 | D51: 44013 | G51: 6 | H51: yes | I51: 45184 | M51: Cristian Pellegrini | N51: Gaia Seghezzi | O51: cliente | Q51: Sales Expander | R51: F.LLI SALANTI SRL | T51: Associazione Artigiani | U51: Business Expander | V51: Lost | AJ51: 8000 | AK51: 100 | AL51: 8000 | AM51: 100 | AN51: 8000 | AO51: 100 | AP51: 8000 | AQ51: 100 | AT51: ASSOART | AV51: NO | AX51: SI
A52: 61 | B52: AAB_OMA di Martinelli e Beltrami_CR | C52: 7000 | D52: 44013 | G52: 6 | H52: yes | I52: 45184 | M52: Cristian Pellegrini | N52: Gaia Seghezzi | O52: cliente | Q52: Sales Expander | R52: O.M.A. di Martinelli e Beltrami S.r.l. | T52: Associazione Artigiani | U52: Business Expander | V52: Lost | AD52: 34.1875 | AJ52: 7000 | AK52: 100 | AL52: 7000 | AM52: 100 | AN52: 7000 | AO52: 100 | AP52: 7000 | AQ52: 100 | AT52: ASSOART | AV52: NO | AX52: NO
A53: 62 | B53: AAB_DELTA COVER _CR | C53: 8000 | D53: 44013 | G53: 6 | H53: yes | I53: 45184 | M53: Cristian Pellegrini | N53: Gaia Seghezzi | O53: cliente | Q53: Sales Expander | R53: Delta Cover s.r.l. | T53: Associazione Artigiani | U53: Business Expander | V53: Lost | AD53: 74 | AJ53: 8000 | AK53: 100 | AL53: 8000 | AM53: 100 | AN53: 8000 | AO53: 100 | AP53: 8000 | AQ53: 100 | AT53: ASSOART | AV53: NO | AX53: SI
A54: 63 | B54: AAB_DELTA COVER _CR | C54: 1650 | D54: 43831 | G54: 1 | H54: yes | I54: 44859 | J54: 100 | L54: 19B036 | M54: Cristian Pellegrini | N54: Gaia Seghezzi | O54: cliente | Q54: Sales Expander | R54: Delta Cover s.r.l. | T54: Associazione Artigiani | U54: Business Expander | V54: Won | W54: 800 | Y54: 256 | AB54: 100 | AJ54: 1650 | AK54: 100 | AL54: 1650 | AM54: 100 | AN54: 1394 | AO54: 84.484848 | AP54: 1650 | AQ54: 100 | AT54: ASSOART | AV54: NO | AX54: NO
A55: 64 | B55: AAB_KRONOS SRL | C55: 1337 | D55: 43831 | G55: 1 | H55: yes | I55: 44601 | J55: 100 | L55: 19B038 | M55: Valentina Premoli | N55: Gaia Seghezzi | O55: cliente | Q55: Sales Expander | R55: Kronos Srl | T55: Associazione Artigiani | U55: Business Expander | V55: Won | W55: 800 | Y55: 256 | AB55: 100 | AJ55: 1337 | AK55: 100 | AL55: 1337 | AM55: 100 | AN55: 1081 | AO55: 80.852655 | AP55: 1337 | AQ55: 100 | AT55: ASSOART | AU55: Altro | AV55: NO | AX55: SI
A56: 65 | B56: AAB_OFFICINA MECCANICA CAVALLI | C56: 450 | D56: 43831 | G56: 1 | H56: yes | I56: 44601 | J56: 100 | L56: 19B039 | M56: Valentina Premoli | N56: Gaia Seghezzi | O56: cliente | Q56: Sales Expander | R56: Officina Meccanica Cavalli Snc | T56: Associazione Artigiani | U56: Business Expander | V56: Won | W56: 400 | Y56: 128 | AB56: 100 | AJ56: 450 | AK56: 100 | AL56: 450 | AM56: 100 | AN56: 322 | AO56: 71.555556 | AP56: 450 | AQ56: 100 | AT56: ASSOART | AU56: Meccanica | AV56: NO | AX56: SI
A57: 66 | B57: AAB_STILL ALLUMINIO SERRAMENTI SAS | C57: 7000 | D57: 44013 | G57: 6 | H57: yes | I57: 45184 | M57: Cristian Pellegrini | N57: Gaia Seghezzi | O57: cliente | Q57: Sales Expander | R57: STILL ALLUMINIO SERRAMENTI SAS | T57: Associazione Artigiani | U57: Business Expander | V57: Lost | AJ57: 7000 | AK57: 100 | AL57: 7000 | AM57: 100 | AN57: 7000 | AO57: 100 | AP57: 7000 | AQ57: 100 | AT57: ASSOART | AV57: NO | AX57: NO
A58: 67 | B58: AAB BS_CHERUBINI | C58: 14000 | D58: 44197 | G58: 6 | H58: yes | I58: 45184 | M58: Cristian Pellegrini | N58: Gaia Seghezzi | O58: cliente | Q58: Ricerca Agenti Distributori | R58: CHERUBINI | T58: Associazione Artigiani | U58: Business Expander | V58: Lost | AD58: 16 | AJ58: 14000 | AK58: 100 | AL58: 14000 | AM58: 100 | AN58: 14000 | AO58: 100 | AP58: 14000 | AQ58: 100 | AT58: ASSOART | AV58: NO | AX58: NO
A59: 68 | B59: AAB_TECNOINCOLLAGGI | C59: 7000 | D59: 44013 | G59: 6 | H59: yes | I59: 45184 | M59: Cristian Pellegrini | N59: Gaia Seghezzi | O59: cliente | Q59: Sales Expander | R59: TECNOINCOLLAGGI | T59: Associazione Artigiani | U59: Business Expander | V59: Lost | AJ59: 7000 | AK59: 100 | AL59: 7000 | AM59: 100 | AN59: 7000 | AO59: 100 | AP59: 7000 | AQ59: 100 | AT59: ASSOART | AV59: NO | AX59: NO
A60: 69 | B60: AAB_TONIN DOMENICO | C60: 7000 | D60: 44013 | G60: 6 | H60: yes | I60: 44497 | M60: Cristian Pellegrini | N60: Gaia Seghezzi | O60: cliente | Q60: Sales Expander | R60: TONIN DOMENICO | T60: Associazione Artigiani | U60: Business Expander | V60: Lost | AJ60: 7000 | AK60: 100 | AL60: 7000 | AM60: 100 | AN60: 7000 | AO60: 100 | AP60: 7000 | AQ60: 100 | AT60: ASSOART | AV60: NO | AX60: NO
A61: 70 | B61: AAB_EQUA SRL | C61: 7000 | D61: 44013 | G61: 6 | H61: yes | I61: 45184 | M61: Cristian Pellegrini | N61: Gaia Seghezzi | O61: cliente | Q61: Sales Expander | R61: EQUA SRL | T61: Associazione Artigiani | U61: Business Expander | V61: Lost | AJ61: 7000 | AK61: 100 | AL61: 7000 | AM61: 100 | AN61: 7000 | AO61: 100 | AP61: 7000 | AQ61: 100 | AT61: ASSOART | AV61: NO | AX61: NO
A62: 71 | B62: AAB_GBM SRL | C62: 7000 | D62: 44013 | G62: 6 | H62: yes | I62: 45184 | M62: Cristian Pellegrini | N62: Gaia Seghezzi | O62: cliente | Q62: Sales Expander | R62: GBM SRL | T62: Associazione Artigiani | U62: Business Expander | V62: Lost | AJ62: 7000 | AK62: 100 | AL62: 7000 | AM62: 100 | AN62: 7000 | AO62: 100 | AP62: 7000 | AQ62: 100 | AT62: ASSOART | AV62: NO | AX62: NO
A63: 72 | B63: AAB_HABITAT ITALIA | C63: 8000 | D63: 44013 | G63: 6 | H63: yes | I63: 44497 | M63: Cristian Pellegrini | N63: Gaia Seghezzi | O63: cliente | Q63: Sales Expander | R63: HABITAT ITALIA | T63: Associazione Artigiani | U63: Business Expander | V63: Lost | AJ63: 8000 | AK63: 100 | AL63: 8000 | AM63: 100 | AN63: 8000 | AO63: 100 | AP63: 8000 | AQ63: 100 | AT63: ASSOART | AV63: NO | AX63: NO
A64: 73 | B64: AAB BS_DELMEC DI DELPERO TOMMASO & C.SNC | C64: 7000 | D64: 44562 | G64: 6 | H64: yes | I64: 45184 | M64: Cristian Pellegrini | N64: Gaia Seghezzi | O64: cliente | Q64: Sales Expander | R64: DELMEC DI DELPERO TOMMASO &amp; C.SNC | T64: Associazione Artigiani | U64: Business Expander | V64: Lost | AJ64: 7000 | AK64: 100 | AL64: 7000 | AM64: 100 | AN64: 7000 | AO64: 100 | AP64: 7000 | AQ64: 100 | AR64: 29/08/22 | AS64: 00/00/00 | AT64: ASSOART | AU64: Meccanica | AV64: NO | AX64: NO
A65: 74 | B65: AAB_Torneria Automatica | C65: 7000 | D65: 44013 | G65: 6 | H65: yes | I65: 45184 | M65: Cristian Pellegrini | N65: Gaia Seghezzi | O65: cliente | Q65: Sales Expander | R65: Torneria Automatica S.N.C. Di Beloli Fladimir &amp; C. | T65: Associazione Artigiani | U65: Business Expander | V65: Lost | AJ65: 7000 | AK65: 100 | AL65: 7000 | AM65: 100 | AN65: 7000 | AO65: 100 | AP65: 7000 | AQ65: 100 | AT65: ASSOART | AV65: NO | AX65: NO
A66: 75 | B66: AAB_ELVIPLAST | C66: 9000 | D66: 44562 | G66: 6 | H66: yes | I66: 45184 | M66: Cristian Pellegrini | N66: Gaia Seghezzi | O66: cliente | Q66: Sales Expander | R66: ELVIPLAST | T66: Associazione Artigiani | U66: Business Expander | V66: Lost | AJ66: 9000 | AK66: 100 | AL66: 9000 | AM66: 100 | AN66: 9000 | AO66: 100 | AP66: 9000 | AQ66: 100 | AR66: 29/08/22 | AS66: 00/00/00 | AT66: ASSOART | AU66: Gomma e plastica | AV66: NO | AX66: NO
A67: 76 | B67: Ecover | C67: 37852 | D67: 43831 | G67: 12 | H67: yes | I67: 44859 | J67: 100 | L67: 20B105 | M67: Cristian Pellegrini | N67: Alessandra Garlini | O67: cliente | Q67: OLD_Temporary Export Management | R67: Ecover Srl | U67: Business Expander | V67: Won | W67: 30717 | X67: 30717 | AA67: 30717 | AD67: 74 | AJ67: 7135 | AK67: 18.849731 | AL67: 7135 | AM67: 18.849731 | AN67: 7135 | AO67: 18.849731 | AP67: 7135 | AQ67: 18.849731 | AV67: NO | AX67: SI
A68: 77 | B68: OTIM_TEM 19/20 | C68: 10000 | D68: 43739 | G68: 10 | H68: yes | I68: 44987 | J68: 100 | L68: 19B021 | M68: Annalisa Surini | N68: Alessandra Garlini | O68: cliente | Q68: OLD_Temporary Export Management | R68: Otim Srl | U68: Business Expander | V68: Won | W68: 9600 | Y68: 3072 | AB68: 100 | AC68: 36.72 | AD68: 1128 | AI68: 1128 | AJ68: 10000 | AK68: 100 | AL68: 10000 | AM68: 100 | AN68: 6928 | AO68: 69.28 | AP68: 8872 | AQ68: 88.72 | AT68: CONFIMI BG | AV68: SI | AX68: SI
A69: 78 | B69: P.IVA_GDM BENNE | C69: 20000 | D69: 43922 | G69: 9 | H69: yes | I69: 44601 | J69: 100 | L69: 20B120 | M69: Federica Perico | N69: Claudia Nikolai | O69: cliente | Q69: OLD_Temporary Export Management | R69: G.D.M. SNC DI GIUSEPPE DI MAURO &amp; C. | U69: Business Expander | V69: Won | W69: 18400 | X69: 10000 | Y69: 2464 | AB69: 100 | AC69: 138.39 | AD69: 3596.5 | AI69: 3596.5 | AJ69: 10000 | AK69: 50 | AL69: 20000 | AM69: 100 | AN69: 7536 | AO69: 37.68 | AP69: 16403.5 | AQ69: 82.0175 | AU69: Meccanica | AV69: NO | AX69: SI
A70: 79 | B70: CIM LASER | C70: 10000 | D70: 44197 | G70: 6 | H70: yes | I70: 45184 | M70: Cristian Pellegrini | N70: Gaia Seghezzi | O70: cliente | Q70: Sales Expander | R70: C.I.M. SRL | U70: Business Expander | V70: Lost | W70: 14400 | Y70: 3840 | AB70: 100 | AJ70: 10000 | AK70: 100 | AL70: 10000 | AM70: 100 | AN70: 6160 | AO70: 61.6 | AP70: 10000 | AQ70: 100 | AV70: NO | AX70: NO
A71: 80 | B71: Elettroarmature | C71: 500 | D71: 43831 | G71: 12 | H71: yes | I71: 44596 | J71: 100 | L71: 19B010 | M71: Alessandra Garlini | N71: Alessandra Garlini | O71: cliente | Q71: OLD_Temporary Export Management | R71: Elettroarmature S.R.L. | U71: Business Expander | V71: Won | W71: 4800 | Y71: 1656 | AB71: 100 | AC71: 11.81 | AD71: 293.5 | AI71: 293.5 | AJ71: 500 | AK71: 100 | AL71: 500 | AM71: 100 | AN71: -1156 | AO71: -231.2 | AP71: 206.5 | AQ71: 41.3 | AV71: NO | AX71: SI
A72: 81 | B72: Emsibeth 2021 | C72: 7000 | D72: 44197 | G72: 6 | H72: yes | I72: 44601 | J72: 100 | L72: 21B111 | M72: Valentina Premoli | N72: Claudia Nikolai | O72: cliente | Q72: Ricerca Agenti Distributori | R72: EMSIBETH Spa | U72: Business Expander | V72: Won | W72: 4490 | X72: 490 | Y72: 1320 | AA72: 490 | AB72: 100 | AC72: 150.69 | AD72: 1778 | AI72: 1778 | AJ72: 6510 | AK72: 93 | AL72: 7000 | AM72: 100 | AN72: 5190 | AO72: 74.142857 | AP72: 5222 | AQ72: 74.6 | AT72: COSM ITALIA | AU72: Cosmetica | AV72: NO | AX72: NO
A73: 82 | B73: Athena's | C73: 5000 | D73: 44105 | G73: 3 | H73: yes | I73: 44601 | J73: 100 | L73: 20B165 | M73: Valentina Premoli | N73: Claudia Nikolai | O73: cliente | Q73: Ricerca Agenti Distributori | R73: Athena's | U73: Business Expander | V73: Won | W73: 350 | X73: 350 | AD73: 2122 | AJ73: 4650 | AK73: 93 | AL73: 4650 | AM73: 93 | AN73: 4650 | AO73: 93 | AP73: 4650 | AQ73: 93 | AT73: COSM ITALIA | AU73: Cosmetica | AV73: NO | AX73: NO
A74: 83 | B74: MULTI COSMETICA_Coind Cosmetics | C74: 7000 | D74: 44013 | G74: 6 | H74: yes | I74: 44497 | M74: Claudia Nikolai | N74: Claudia Nikolai | O74: cliente | Q74: Organizzazione di Incoming | R74: Coind Cosmetics | U74: FINC | V74: Lost | AJ74: 7000 | AK74: 100 | AL74: 7000 | AM74: 100 | AN74: 7000 | AO74: 100 | AP74: 7000 | AQ74: 100 | AT74: COSM ITALIA | AV74: NO | AX74: NO
A75: 84 | B75: SORA SRL_SE 20-21 | C75: 9000 | D75: 44105 | G75: 6 | H75: yes | I75: 44599 | J75: 100 | L75: 20B169 | M75: Benedetta Bianchi | N75: Alessandra Garlini | O75: cliente | Q75: Sales Expander | R75: SORA SRL | U75: Business Expander | V75: Won | W75: 6800 | Y75: 2216 | AB75: 100 | AC75: 125.39 | AD75: 2757 | AI75: 2757 | AJ75: 9000 | AK75: 100 | AL75: 9000 | AM75: 100 | AN75: 6784 | AO75: 75.377778 | AP75: 6243 | AQ75: 69.366667 | AU75: Meccanica | AV75: NO | AX75: NO | AY75: Italia
A76: 85 | B76: APA MONZA_LE FEDI GERLA | C76: 7000 | D76: 43983 | G76: 6 | H76: yes | I76: 45184 | M76: Cristian Pellegrini | N76: Gaia Seghezzi | O76: cliente | Q76: Sales Expander | R76: LE FEDI GERLA | U76: Business Expander | V76: Lost | AJ76: 7000 | AK76: 100 | AL76: 7000 | AM76: 100 | AN76: 7000 | AO76: 100 | AP76: 7000 | AQ76: 100 | AT76: APA MONZA | AV76: NO | AX76: NO
A77: 86 | B77: APA MONZA_GISLON PUBBLICITA&#x27; | C77: 7000 | D77: 44075 | G77: 6 | H77: yes | I77: 45184 | M77: Cristian Pellegrini | N77: Gaia Seghezzi | O77: cliente | Q77: Sales Expander | R77: GISLON PUBBLICITA&#x27; | U77: Business Expander | V77: Lost | AD77: 96 | AJ77: 7000 | AK77: 100 | AL77: 7000 | AM77: 100 | AN77: 7000 | AO77: 100 | AP77: 7000 | AQ77: 100 | AT77: APA MONZA | AV77: NO | AX77: NO
A78: 87 | B78: APA MONZA_ERNANI ITALIAN COFEE | C78: 7000 | D78: 44075 | G78: 6 | H78: yes | I78: 45184 | M78: Cristian Pellegrini | N78: Gaia Seghezzi | O78: cliente | Q78: Sales Expander | R78: ERNANI ITALIAN COFEE | U78: Business Expander | V78: Lost | AJ78: 7000 | AK78: 100 | AL78: 7000 | AM78: 100 | AN78: 7000 | AO78: 100 | AP78: 7000 | AQ78: 100 | AT78: APA MONZA | AV78: NO | AX78: NO
A79: 88 | B79: APA MONZA_FP PROSERPIO | C79: 7000 | D79: 44075 | G79: 6 | H79: yes | I79: 45184 | M79: Cristian Pellegrini | N79: Gaia Seghezzi | O79: cliente | Q79: Sales Expander | R79: FP PROSERPIO | U79: Business Expander | V79: Lost | AJ79: 7000 | AK79: 100 | AL79: 7000 | AM79: 100 | AN79: 7000 | AO79: 100 | AP79: 7000 | AQ79: 100 | AT79: APA MONZA | AV79: NO | AX79: NO
A80: 89 | B80: APA MONZA_TORNOVA | C80: 17000 | D80: 44287 | G80: 12 | H80: yes | I80: 45184 | M80: Cristian Pellegrini | N80: Gaia Seghezzi | O80: cliente | Q80: Sales Expander | R80: TORNOVA | U80: Business Expander | V80: Lost | AJ80: 17000 | AK80: 100 | AL80: 17000 | AM80: 100 | AN80: 17000 | AO80: 100 | AP80: 17000 | AQ80: 100 | AT80: APA MONZA | AV80: NO | AX80: NO
A81: 90 | B81: Comac Srl | C81: 4500 | D81: 44013 | G81: 6 | H81: yes | I81: 44497 | M81: Cristian Pellegrini | N81: Alessandra Garlini | O81: cliente | Q81: Sales Expander | R81: Comac Srl | U81: Business Expander | V81: Lost | AJ81: 4500 | AK81: 100 | AL81: 4500 | AM81: 100 | AN81: 4500 | AO81: 100 | AP81: 4500 | AQ81: 100 | AV81: NO | AX81: NO
A82: 91 | B82: AAB_QUADRI | C82: 500 | D82: 43831 | G82: 1 | H82: yes | I82: 44859 | J82: 100 | L82: 19B041 | M82: Cristian Pellegrini | N82: Gaia Seghezzi | O82: cliente | Q82: Sales Expander | R82: Quadri Montaggi Meccanici di Quadri Roberto | T82: Associazione Artigiani | U82: Business Expander | V82: Won | W82: 800 | Y82: 256 | AB82: 100 | AJ82: 500 | AK82: 100 | AL82: 500 | AM82: 100 | AN82: 244 | AO82: 48.8 | AP82: 500 | AQ82: 100 | AT82: ASSOART | AV82: NO | AX82: NO
A83: 92 | B83: AAB_MAPELLI SRL | C83: 7000 | D83: 44013 | G83: 6 | H83: yes | I83: 45184 | M83: Cristian Pellegrini | N83: Gaia Seghezzi | O83: cliente | Q83: Sales Expander | R83: MAPELLI SRL | T83: Associazione Artigiani | U83: Business Expander | V83: Lost | AJ83: 7000 | AK83: 100 | AL83: 7000 | AM83: 100 | AN83: 7000 | AO83: 100 | AP83: 7000 | AQ83: 100 | AT83: ASSOART | AV83: NO | AX83: SI
A84: 93 | B84: AAB_VALTORTA SRL | C84: 12000 | D84: 43983 | G84: 12 | H84: yes | I84: 45184 | M84: Valentina Premoli | N84: Gaia Seghezzi | O84: cliente | Q84: Sales Expander | R84: VALTORTA Srl | T84: Associazione Artigiani | U84: Business Expander | V84: Lost | AJ84: 12000 | AK84: 100 | AL84: 12000 | AM84: 100 | AN84: 12000 | AO84: 100 | AP84: 12000 | AQ84: 100 | AT84: ASSOART | AV84: NO | AX84: SI
A85: 94 | B85: AAB_MB ITALIA | C85: 5000 | D85: 44013 | G85: 6 | H85: yes | I85: 44497 | M85: Cristian Pellegrini | N85: Claudia Nikolai | O85: cliente | Q85: Sales Expander | R85: MB ITALIA | T85: Associazione Artigiani | U85: Business Expander | V85: Lost | AJ85: 5000 | AK85: 100 | AL85: 5000 | AM85: 100 | AN85: 5000 | AO85: 100 | AP85: 5000 | AQ85: 100 | AT85: ASSOART | AV85: NO | AX85: NO
A86: 95 | B86: AAB_SD LASER | C86: 12000 | D86: 43983 | G86: 12 | H86: yes | I86: 45184 | M86: Elena Barcella | N86: Gaia Seghezzi | O86: cliente | Q86: Sales Expander | R86: SD Laser | T86: Associazione Artigiani | U86: Business Expander | V86: Lost | AJ86: 12000 | AK86: 100 | AL86: 12000 | AM86: 100 | AN86: 12000 | AO86: 100 | AP86: 12000 | AQ86: 100 | AT86: ASSOART | AV86: NO | AX86: SI
A87: 96 | B87: Escaffe BE | C87: 18900 | D87: 43831 | G87: 9 | H87: yes | I87: 44596 | J87: 100 | L87: 19X301 | M87: Alessandra Garlini | N87: Alessandra Garlini | O87: cliente | Q87: OLD_Temporary Export Management | R87: Escaffe Srl | U87: Business Expander | V87: Won | W87: 15870 | X87: 1470 | Y87: 5328 | AA87: 1470 | AB87: 100 | AC87: 81.6 | AD87: 4347.5 | AI87: 4347.5 | AJ87: 17430 | AK87: 92.222222 | AL87: 18900 | AM87: 100 | AN87: 12102 | AO87: 64.031746 | AP87: 14552.5 | AQ87: 76.997354 | AV87: SI | AX87: NO | AZ87: BE-COM
A88: 97 | B88: Scent Company BE | C88: 6000 | D88: 43862 | G88: 2 | H88: yes | I88: 44596 | J88: 100 | L88: 20X104 | M88: Annalisa Surini | N88: Alessandra Garlini | O88: cliente | Q88: OLD_Temporary Export Management | R88: Scent Company Srl | U88: Business Expander | V88: Won | W88: 2100 | Y88: 672 | AB88: 100 | AC88: 8.59 | AD88: 132 | AI88: 132 | AJ88: 6000 | AK88: 100 | AL88: 6000 | AM88: 100 | AN88: 5328 | AO88: 88.8 | AP88: 5868 | AQ88: 97.8 | AU88: Altro | AV88: SI | AX88: NO | AZ88: BE-COM
A89: 98 | B89: Stracciatella BE | C89: 500 | D89: 43831 | G89: 12 | H89: yes | I89: 44596 | J89: 100 | L89: 20X111 | M89: Elena Barcella | N89: Angela Pezzoli | O89: cliente | Q89: OLD_Temporary Export Management | R89: Ascom Bergamo | U89: Business Expander | V89: Won | W89: 4000 | Y89: 1280 | AB89: 100 | AJ89: 500 | AK89: 100 | AL89: 500 | AM89: 100 | AN89: -780 | AO89: -156 | AP89: 500 | AQ89: 100 | AV89: NO | AX89: SI | AZ89: BE-EVKMR
A90: 99 | B90: Vozzi Ermelinda_SE_20/21 | C90: 15844 | D90: 43952 | G90: 15 | H90: yes | I90: 44596 | J90: 100 | L90: 20X110 | M90: Annalisa Surini | N90: Alessandra Garlini | O90: cliente | Q90: Sales Expander | R90: Vozzi Ermelinda | U90: Business Expander | V90: Won | W90: 12645 | X90: 645 | Y90: 3840 | AA90: 645 | AB90: 100 | AC90: 80.63 | AD90: 2511.5 | AI90: 2511.5 | AJ90: 15199 | AK90: 95.929058 | AL90: 15844 | AM90: 100 | AN90: 11359 | AO90: 71.692754 | AP90: 13332.5 | AQ90: 84.148574 | AU90: Food | AV90: SI | AX90: NO | AY90: Italia | AZ90: BE-COM
A91: 100 | B91: CARNI LIMONGI BE | C91: 12000 | D91: 43983 | G91: 7 | H91: yes | I91: 44497 | L91: 20X108 | M91: Cristian Pellegrini | N91: Alessandra Garlini | O91: cliente | Q91: OLD_Temporary Export Management | R91: CARNI LIMONGI SRL | U91: Business Expander | V91: Lost | AJ91: 12000 | AK91: 100 | AL91: 12000 | AM91: 100 | AN91: 12000 | AO91: 100 | AP91: 12000 | AQ91: 100 | AV91: SI | AX91: NO | AZ91: BE-COM
A92: 101 | B92: CARPENTERIA NICOLA POTENZA BE | C92: 8000 | D92: 44013 | G92: 6 | H92: yes | I92: 44497 | L92: 20X109 | M92: Cristian Pellegrini | N92: Alessandra Garlini | O92: cliente | Q92: OLD_Temporary Export Management | R92: CARPENTERIA NICOLA POTENZA SNC | U92: Business Expander | V92: Lost | AJ92: 8000 | AK92: 100 | AL92: 8000 | AM92: 100 | AN92: 8000 | AO92: 100 | AP92: 8000 | AQ92: 100 | AV92: SI | AX92: NO | AZ92: BE-COM
A93: 102 | B93: AAB_Blåkläder Italia_20/21SE | C93: 7200 | D93: 44013 | G93: 7 | H93: yes | I93: 44596 | J93: 100 | L93: 20B147 | M93: Annalisa Surini | N93: Gaia Seghezzi | O93: cliente | Q93: Sales Expander | R93: Blåkläder Italia SRL | T93: Associazione Artigiani | U93: Business Expander | V93: Won | W93: 6000 | Y93: 1920 | AB93: 100 | AC93: 243.75 | AD93: 4133 | AI93: 4133 | AJ93: 7200 | AK93: 100 | AL93: 7200 | AM93: 100 | AN93: 5280 | AO93: 73.333333 | AP93: 3067 | AQ93: 42.597222 | AT93: ASSOART | AU93: Tessile e abbigliamento | AV93: NO | AX93: NO | AY93: Italia
A94: 103 | B94: 2020 Affiancamento Polypool | C94: 45000 | D94: 43831 | G94: 12 | H94: yes | I94: 44497 | J94: 100 | L94: 20B125 | M94: Cristian Pellegrini | N94: Giovanna Ricuperati | O94: cliente | Q94: Temporary Marketing Management | R94: Polypool Spa | U94: Business Expander | V94: Won | W94: 38400 | Y94: 14208 | AB94: 100 | AC94: 61.2 | AD94: 8695 | AI94: 8695 | AJ94: 45000 | AK94: 100 | AL94: 45000 | AM94: 100 | AN94: 30792 | AO94: 68.426667 | AP94: 36305 | AQ94: 80.677778 | AV94: NO | AX94: SI
A95: 104 | B95: Affiancamento Scame 2019-20 | C95: 24000 | D95: 43831 | G95: 3 | H95: yes | I95: 44596 | J95: 100 | L95: 19B024 | M95: Francesca Gritti | N95: Giovanna Ricuperati | O95: cliente | Q95: Temporary Marketing Management | R95: Scame Parre Spa | U95: Business Expander | V95: Won | W95: 10800 | Y95: 3376 | AB95: 100 | AC95: 22.66 | AD95: 835 | AI95: 835 | AJ95: 24000 | AK95: 100 | AL95: 24000 | AM95: 100 | AN95: 20624 | AO95: 85.933333 | AP95: 23165 | AQ95: 96.520833 | AU95: Elettrico/Elettronico | AV95: NO | AX95: SI
A96: 105 | B96: Grazioli Tem | C96: 6000 | D96: 43831 | G96: 12 | H96: yes | I96: 44970 | J96: 100 | L96: 20B107 | M96: Cristian Pellegrini | N96: Alessandra Garlini | O96: cliente | Q96: OLD_Temporary Export Management | R96: Grazioli F.lli Angelo | U96: Business Expander | V96: Won | W96: 4400 | X96: 4400 | AA96: 4400 | AD96: 60 | AJ96: 1600 | AK96: 26.666667 | AL96: 1600 | AM96: 26.666667 | AN96: 1600 | AO96: 26.666667 | AP96: 1600 | AQ96: 26.666667 | AU96: Meccanica | AV96: NO | AX96: SI | AY96: Germania, Austria, Svizzera
A97: 106 | B97: Affiancamento Santalessandro | C97: 6000 | D97: 43831 | G97: 3 | H97: yes | I97: 44621 | J97: 100 | L97: 19B028 | M97: Valentina Bucca | N97: Giovanna Ricuperati | O97: cliente | Q97: Temporary Marketing Management | R97: Fondazione SantAlessandro | U97: Business Expander | V97: Won | W97: 12000 | Y97: 3840 | AB97: 100 | AC97: 7.25 | AD97: 292 | AI97: 292 | AJ97: 6000 | AK97: 100 | AL97: 6000 | AM97: 100 | AN97: 2160 | AO97: 36 | AP97: 5708 | AQ97: 95.133333 | AU97: Altro | AV97: NO | AX97: SI
A98: 107 | B98: Sitip Analisi preliminare | C98: 7000 | D98: 43831 | G98: 4 | H98: yes | I98: 44595 | J98: 100 | L98: 20X102 | M98: Francesca Poletti | N98: Giovanna Ricuperati | O98: cliente | Q98: Assessment | R98: Sitip Spa | S98: Silvana Pezzoli | U98: Business Expander | V98: Won | W98: 3600 | Y98: 960 | AB98: 100 | AC98: 626.04 | AD98: 6044 | AI98: 6044 | AJ98: 7000 | AK98: 100 | AL98: 7000 | AM98: 100 | AN98: 6040 | AO98: 86.285714 | AP98: 956 | AQ98: 13.657143 | AU98: Tessile e abbigliamento | AV98: NO | AX98: NO | AZ98: BE-COM | BB98: 98-2019
A99: 108 | B99: LTE BE | C99: 14950 | D99: 43831 | G99: 12 | H99: yes | I99: 44596 | J99: 100 | L99: 20X113 | M99: Francesca Gritti | N99: Alessandra Garlini | O99: cliente | R99: Lte impianti s.r.l | U99: Business Expander | V99: Won | W99: 16000 | Y99: 4432 | AB99: 100 | AC99: 86.54 | AD99: 3259 | AI99: 3259 | AJ99: 14950 | AK99: 100 | AL99: 14950 | AM99: 100 | AN99: 10518 | AO99: 70.354515 | AP99: 11691 | AQ99: 78.200669 | AU99: Impianti | AV99: NO | AX99: NO | AZ99: BE-COM
A100: 109 | B100: Multifood | C100: 12000 | D100: 43831 | G100: 6 | H100: yes | I100: 44601 | J100: 100 | L100: 19B018 | M100: Valentina Premoli | N100: Alessandra Garlini | O100: cliente | R100: Multifood | U100: Business Expander | V100: Won | W100: 15100 | X100: 2300 | Y100: 4256 | AB100: 100 | AC100: 45.98 | AD100: 1763.5 | AI100: 1763.5 | AJ100: 9700 | AK100: 80.833333 | AL100: 12000 | AM100: 100 | AN100: 5444 | AO100: 45.366667 | AP100: 10236.5 | AQ100: 85.304167 | AU100: Food | AV100: NO | AX100: SI
...

Sheet OLD
A1: Project | B1: Estimate | C1: Check planning | D1: Start | E1: Anno | F1: Due_Date | G1: Duration | H1: Archived | I1: Archived_Date | J1: Probability | K1: Client_PO | L1: Job_Order | M1: PM | N1: Supervisor | O1: Note
A2: 110 Laude_sales expander | B2: 11000 | D2: 46082 | G2: 5 | H2: no | J2: 100 | L2: 26B139 | M2: Lisa Pezzali | N2: Cristian Pellegrini
A3: AAB_ALDEGANI_SE 26 | B3: 12700 | D3: 46113 | G3: 12 | H3: no | J3: 100 | L3: 26B137 | M3: Giulia Pizzati | N3: Cristian Pellegrini
A4: AAB_CORNA IMPIANTI SRL | B4: 10000 | D4: 45992 | G4: 7 | H4: no | J4: 100 | L4: 25B200 | M4: Lisa Pezzali | N4: Annalisa Surini
A5: AAB_CRIMAR_SE 26/27 | B5: 16200 | D5: 46113 | G5: 12 | H5: no | J5: 100 | L5: 26B136 | M5: Lisa Pezzali | N5: Francesca Gritti
A6: AAB_DOMINO_SE 26 | B6: 16200 | D6: 46054 | G6: 12 | H6: no | J6: 100 | L6: 26B116 | M6: Silvia Cortinovis | N6: OK NO | O6: Vede Franci Gritti negli allineamenti con Silvia
A7: AAB_FORMENTI_SE 26_Gestione | B7: 3375 | D7: 46023 | G7: 6 | H7: no | J7: 100 | L7: 26X104 | M7: Silvia Cortinovis | N7: Annalisa Surini
A8: AAB_FRATUS_SE 2026 | B8: 16200 | D8: 45962 | G8: 12 | H8: no | J8: 100 | L8: 25X119 | M8: Ilaria Colleoni | N8: Gaia Seghezzi
A9: AAB_GRAFFIDEA_SE 2026 | B9: 13000 | D9: 46054 | G9: 12 | H9: no | J9: 100 | L9: 26B121 | M9: Lisa Pezzali | N9: Cristian Pellegrini
A10: AAB_KITERM SE 2025-26 | B10: 10500 | D10: 45931 | G10: 12 | H10: no | J10: 100 | L10: 25B193 | M10: Lisa Pezzali | N10: Cristian Pellegrini
A11: AAB_ML ENGRAVING_ SE 26 | B11: 27000 | D11: 46023 | G11: 12 | H11: no | J11: 100 | L11: 26B108 | M11: Silvia Cortinovis | N11: Annalisa Surini
A12: AAB_ML ENGRAVING_EMILIA_SE FINE 25 | B12: 13770 | D12: 45748 | G12: 9 | H12: no | J12: 100 | L12: 25B135 | M12: Silvia Cortinovis | O12: Chiuso? Da archiviare?
A13: AAB_ML ENGRAVING_PIEMONTE FINE 25 | B13: 12240 | D13: 45778 | G13: 8 | H13: no | J13: 100 | L13: 25B136 | M13: Silvia Cortinovis | O13: Chiuso? Da archiviare?
A14: AAB_OFFICINE GAITI_SE 26/27 | B14: 16200 | D14: 46113 | G14: 12 | H14: no | J14: 100 | L14: 26B131 | M14: Lisa Pezzali | N14: Annalisa Surini
A15: AAB_OMCS PLAST_SE 26 | B15: 16200 | D15: 46054 | G15: 12 | H15: no | J15: 100 | L15: 26B119 | M15: Chiara Ballabio | N15: Cristian Pellegrini | O15: PM nuovo post Poletti / Capire chi subentra come supervisor
A16: AAB_OMI SRL_SE | B16: 2800 | D16: 45870 | G16: 2 | H16: no | J16: 100 | L16: 25B179 | M16: Gaia Seghezzi | O16: Chiuso? Da archiviare?
A17: AAB_Plastic technology_SE | B17: 17200 | D17: 45992 | G17: 13 | H17: no | J17: 100 | L17: 25B201 | M17: Lisa Pezzali | N17: Annalisa Surini
A18: AAB_PLASTIMAX_SE 25/26 | B18: 16200 | D18: 45809 | G18: 12 | H18: no | J18: 100 | L18: 25B143 | M18: FRANCESCA BOSIS | N18: Francesca Gritti
A19: AAB_PROJECT PACKAGING_SE 26 | B19: 11700 | D19: 46054 | G19: 12 | H19: no | J19: 100 | L19: 26B115 | M19: Ilaria Colleoni
A20: AAB_VALMATECH_SE 25-26 | B20: 16200 | D20: 45901 | G20: 12 | H20: no | J20: 100 | L20: 25B157 | M20: Giulia Pizzati | N20: Annalisa Surini
A21: AAB_VALMATECH_warm up 25 | B21: 900 | D21: 45839 | G21: 1 | H21: no | J21: 100 | L21: 25B157 | M21: Giulia Pizzati | N21: Annalisa Surini
A22: AAB_VERDELLI_SE 26 | B22: 19350 | D22: 46023 | G22: 12 | H22: no | J22: 100 | L22: 26X102 | M22: Annalisa Surini | N22: Annalisa Surini
A23: AGLA_PRE POST FIERA | B23: 6000 | D23: 46023 | G23: 5 | H23: no | J23: 100 | L23: 26B107 | M23: Francesca Poletti | O23: Chiuso? Da archiviare?
A24: AGRICOOLTUR_Market Test | B24: 24000 | D24: 45839 | G24: 10 | H24: no | J24: 100 | L24: 25B176 | M24: Silvia Cortinovis | O24: Chiuso? Da archiviare?
A25: AMBROSETTI_SE 2026 | B25: 24200 | D25: 46054 | G25: 12 | H25: no | J25: 100 | L25: 26B110 | M25: Giulia Pizzati | N25: Cristian Pellegrini
A26: APA MONZA_TEKNOFLUOR_SE25-26 | B26: 15000 | D26: 45901 | G26: 14 | H26: no | J26: 100 | L26: 25B185 | M26: Ilaria Colleoni | N26: Cristian Pellegrini
A27: ARX_SE 2025-26 | B27: 28000 | D27: 45809 | G27: 12 | H27: no | J27: 100 | L27: 25B133 | M27: Giulia Pizzati | N27: Francesca Gritti
A28: Barbiflex_SE 2026 | B28: 30000 | D28: 46174 | G28: 14 | H28: no | J28: 100 | L28: 26B149 | M28: Chiara Ballabio | N28: Annalisa Surini
A29: BCM srl_sales expander | B29: 30000 | D29: 46113 | G29: 12 | H29: no | J29: 100 | L29: 26B155 | M29: Chiara Ballabio | N29: Cristian Pellegrini
A30: BERTOLONI E BOTTURI _SE 25 | B30: 30000 | D30: 45901 | G30: 12 | H30: no | J30: 100 | L30: 25B177 | M30: Gaia Seghezzi | N30: Gaia Seghezzi | O30: In gestione a Gaia Seghezzi in chiusura
A31: BOSCAROL_M&A | B31: 12000 | D31: 45931 | G31: 4 | H31: no | J31: 100 | L31: 25B168 | M31: Silvia Cortinovis | N31: OK NO | O31: Segue Franci Gritti negli allineamenti con Silvia
A32: BOSCAROL_SE 26 | B32: 12000 | D32: 46023 | G32: 12 | H32: no | J32: 100 | L32: 26X101 | M32: Silvia Cortinovis | N32: OK NO | O32: Segue Franci Gritti negli allineamenti con Silvia
A33: Business Trip Food 2025 extra_Calabria | B33: 880 | D33: 45962 | G33: 4 | H33: no | J33: 100 | L33: 25B121 | M33: Giulia Pizzati | O33: Chiuso? Da archiviare?
A34: CE_DRILLING_SE 26 | B34: 20000 | D34: 46023 | G34: 12 | H34: no | J34: 100 | L34: 26X103 | M34: Chiara Ballabio | N34: Annalisa Surini
A35: CEEVER_SE | B35: 27500 | D35: 45901 | G35: 11 | H35: no | J35: 100 | L35: 25B169 | M35: Chiara Ballabio | N35: Cristian Pellegrini
A36: CERCoop_SE | B36: 36678 | D36: 45931 | G36: 12 | H36: no | J36: 100 | L36: 25B208 | M36: Ilaria Colleoni | N36: Cristian Pellegrini
A37: CFG Serramenti_Affiancamento commerciale | B37: 21000 | D37: 46296 | G37: 7 | H37: no | J37: 100 | L37: 26B138 | M37: Annalisa Surini | N37: Annalisa Surini
A38: CFG SERRAMENTI_Assessment | B38: 16200 | D38: 46143 | G38: 3 | H38: no | J38: 100 | L38: 26B138 | M38: Francesca Poletti
A39: CFG Serramenti_Formazione | B39: 5400 | D39: 46235 | G39: 2 | H39: no | J39: 100 | L39: 26B138 | M39: Annalisa Surini | N39: Annalisa Surini
A40: CHEZ MOI ITALIA_ SE 27 | B40: 12000 | D40: 46327 | G40: 5 | H40: no | J40: 90 | M40: Gaia Seghezzi | O40: Parte a Novembre
A41: CMA TEC_SE 2026 | B41: 24000 | D41: 46023 | G41: 12 | H41: no | J41: 100 | L41: 25B206 | M41: Chiara Ballabio | N41: Cristian Pellegrini
A42: COLORI CHIARI_SE 26 | B42: 14000 | D42: 46204 | G42: 7 | H42: no | J42: 90 | M42: Giulia Pizzati | N42: Cristian Pellegrini | O42: Progetto da allocare su Giulia Pizzati
A43: COMINTEC_SE 26 | B43: 18000 | D43: 46143 | G43: 7 | H43: no | J43: 100 | L43: 26B132 | M43: Annalisa Surini | N43: Annalisa Surini
A44: ComoNExT_sales expander | B44: 33500 | D44: 45931 | G44: 12 | H44: no | J44: 100 | L44: 25B189 | M44: Silvia Cortinovis | N44: OK NO | O44: Presidio di Franci Gelmini + segue Franci Gritti negli allineamenti con Silvia
A45: CONF BARI_INCOMING MODA 2026 | B45: 20000 | D45: 46174 | G45: 4 | H45: no | J45: 90 | M45: Ilaria Colleoni | N45: Annalisa Surini
A46: Confcooperative Bergamo_Promozione filiera manifatturiera | B46: 21000 | D46: 46143 | G46: 8 | H46: no | J46: 100 | L46: 26B151 | M46: Cristian Pellegrini | N46: Cristian Pellegrini
A47: E.D. Elettronica Dedicata_SE | B47: 24500 | D47: 45901 | G47: 11 | H47: no | J47: 100 | L47: 25B156 | M47: Chiara Ballabio | N47: Valentina Bucca? | O47: Possiamo liberare Cristina Pellegrini?
A48: E.D. Elettronica Dedicata_TMM | B48: 22800 | D48: 45901 | G48: 11 | H48: no | J48: 100 | L48: 25B156 | M48: Valentina Bucca | N48: Valentina Bucca
A49: ELETTROARMATURE_2026 | B49: 500 | D49: 46023 | G49: 12 | H49: no | J49: 100 | L49: 26B101 | M49: Giulia Pizzati | N49: OK NO | O49: Solo gestione
A50: ENNISWORK_SE 26 | B50: 24000 | D50: 46174 | G50: 12 | H50: no | J50: 100 | L50: 26B146 | M50: Ilaria Colleoni | N50: Cristian Pellegrini
A51: Eurgomma_sales Expander 26 | B51: 14000 | D51: 46082 | G51: 8 | H51: no | J51: 100 | L51: P26B118 | M51: Giulia Pizzati | N51: Cristian Pellegrini
A52: FARETE 2026_Incoming buyer | B52: 4000 | D52: 46113 | G52: 6 | H52: no | J52: 100 | L52: 26B133 | M52: Chiara Ballabio | N52: Annalisa Surini
A53: Faro Club_promozione e sviluppo commerciale | B53: 12500 | D53: 45839 | G53: 6 | H53: no | J53: 100 | L53: 25X115 | M53: Francesca Gelmini | O53: Chiuso? Da archiviare?
A54: FEB ELETTRICA_formazione AI | B54: 580 | D54: 46023 | G54: 1 | H54: no | J54: 100 | L54: 26B104 | M54: Silvia Cortinovis | O54: Chiuso? Da archiviare?
A55: Forelli Pietro_sales Expander | B55: 22000 | D55: 46054 | G55: 11 | H55: no | J55: 100 | L55: 26B111 | M55: Chiara Ballabio | N55: Cristian Pellegrini
A56: FRANTOIO PERILLI_TUTTOFOOD 2026 | B56: 10000 | D56: 46082 | G56: 5 | H56: no | J56: 100 | L56: 26B118 | M56: Chiara Ballabio | O56: Chiuso? Da archiviare?
A57: Gallazzini_formazione | B57: 13000 | D57: 46082 | G57: 6 | H57: no | J57: 100 | L57: 26B129 | M57: Annalisa Surini | N57: Annalisa Surini
A58: GALLAZZINI_SE novembre 25-aprile 26 | B58: 15000 | D58: 45962 | G58: 6 | H58: no | J58: 100 | L58: 25B198 | M58: Giulia Pizzati | O58: Chiuso? Da archiviare?
A59: GATTI PRECORVI_TMM 25-26 | B59: 35630 | D59: 45809 | G59: 10 | H59: no | J59: 100 | L59: 25B150 | M59: Benedetta Bianchi | O59: Chiuso? Da archiviare?
A60: GITRE srl_sales Expander | B60: 34000 | D60: 45992 | G60: 12 | H60: no | J60: 100 | L60: 25B202 | M60: Silvia Cortinovis | N60: Cristian Pellegrini
A61: Glass to Power_Affiancamento strategico di mercato | B61: 18000 | D61: 45717 | G61: 10 | H61: no | J61: 100 | L61: 25B125 | M61: Francesca Gritti | N61: Francesca Gritti
A62: Glass to Power_Consulenza e affiancamento 2026 | B62: 25000 | D62: 46023 | G62: 12 | H62: no | J62: 100 | L62: 26X107 | M62: Francesca Gritti | N62: Francesca Gritti
A63: Grizzly Spa_ SE 26 | B63: 26200 | D63: 46082 | G63: 12 | H63: no | J63: 100 | L63: 26X106 | M63: Giulia Pizzati | N63: Francesca Gritti
A64: Imolafilo_Sales Expander | B64: 29250 | D64: 46143 | G64: 12 | H64: no | J64: 100 | L64: 26B127 | M64: Cristian Pellegrini | N64: Cristian Pellegrini
A65: Kopernicana_sales expander | B65: 38000 | D65: 46143 | G65: 12 | H65: no | J65: 100 | L65: 26B135 | M65: Francesca Gritti | N65: Francesca Gritti
A66: KSENIA SECURITY_Ricerca distributori | B66: 28000 | D66: 46082 | G66: 12 | H66: no | J66: 100 | L66: 26B117 | M66: Ilaria Colleoni | N66: Cristian Pellegrini
A67: Lovato_Analisi sales & mktg | B67: 70000 | D67: 46174 | G67: 6 | H67: no | J67: 90 | M67: Valentina Bucca | N67: Francesca Gritti | O67: Capire chi subentra
A68: Materia Prima_affiancamento luglio dicembre 2026 | B68: 15000 | D68: 46204 | G68: 6 | H68: no | J68: 90 | M68: Silvia Cortinovis | N68: Cristian Pellegrini
A69: Materia Prima_warm up strategico e affiancamento mktg | B69: 18000 | D69: 46023 | G69: 6 | H69: no | J69: 100 | L69: 25B207 | M69: Silvia Cortinovis | N69: Cristian Pellegrini
A70: METANO NORD_Customer Value Program | B70: 13000 | D70: 46174 | G70: 4 | H70: no | J70: 100 | L70: 26B144 | M70: Francesca Gritti | N70: Francesca Gritti
A71: MINONZIO_2026 | B71: 8400 | D71: 46023 | G71: 12 | H71: no | J71: 100 | L71: 26B102 | M71: Giulia Pizzati | N71: OK NO | O71: Solo gestione
A72: MORESCHI_Affiancamento commerciale 2026 | B72: 21600 | D72: 46023 | G72: 12 | H72: no | J72: 100 | L72: 26B106 | M72: Annalisa Surini | N72: Annalisa Surini
A73: Morson Praxis_analisi mercato e market test | B73: 20000 | D73: 46054 | G73: 5 | H73: no | J73: 100 | L73: 25B203 | M73: Silvia Cortinovis | N73: Francesca Gritti
A74: MY PLANT & GARDEN 2027_Promo visitatori | B74: 3500 | D74: 46143 | G74: 8 | H74: no | J74: 100 | L74: 26B141 | M74: Chiara Ballabio | N74: Annalisa Surini
A75: MY PLANT & GARDEN 2027_scouting buyer | B75: 1000 | D75: 46143 | G75: 8 | H75: no | J75: 100 | L75: 26B141 | M75: Chiara Ballabio | N75: Annalisa Surini
A76: MY PLANT & GARDEN 2027_scouting buyer 2 | D76: 46388 | G76: 2 | H76: no | J76: 90 | L76: 26B141 | M76: Chiara Ballabio | N76: Annalisa Surini
A77: MY PLANT & GARDEN 2027_vendita spazi | B77: 2500 | D77: 46143 | G77: 8 | H77: no | J77: 100 | L77: 26B142 | M77: Chiara Ballabio | N77: Annalisa Surini
A78: MY PLANT & GARDEN 2027_vendita spazi 2 | D78: 46388 | G78: 2 | H78: no | J78: 90 | L78: 26B142 | M78: Chiara Ballabio | N78: Annalisa Surini
A79: N-and_analisi strategica + sviluppo commerciale 2026 | B79: 70000 | D79: 46023 | G79: 12 | H79: no | J79: 100 | L79: 25B205 | M79: Giulia Pizzati | N79: Francesca Gritti | O79: Capire chi subentra
A80: NILMA CONTRACT_SE 26 | B80: 20000 | D80: 46143 | G80: 12 | H80: no | J80: 100 | L80: 26B140 | M80: Giulia Pizzati | N80: Francesca Gritti | O80: Segue Franci Gritti negli allineamenti con Silvia
A81: OTIM_SE 2026 | B81: 17150 | D81: 46082 | G81: 12 | H81: no | J81: 100 | L81: 26X108 | M81: Annalisa Surini | N81: Annalisa Surini
A82: PAPERMON_SE 25/26 | B82: 20000 | D82: 45901 | G82: 10 | H82: no | J82: 100 | L82: 25B174 | M82: Silvia Cortinovis | N82: OK NO | O82: Segue Franci Gritti negli allineamenti con Silvia
A83: Papermon_SE 26 | B83: 24000 | D83: 46204 | G83: 12 | H83: no | J83: 100 | L83: 26B150 | M83: Silvia Cortinovis | N83: OK NO | O83: Segue Franci Gritti negli allineamenti con Silvia
A84: Parkair_sales Expander 2026 | B84: 23000 | D84: 46113 | G84: 10 | H84: no | J84: 100 | L84: 26B123 | M84: Silvia Cortinovis | N84: Cristian Pellegrini
A85: PARTEC Srl_SE | B85: 28000 | D85: 46054 | G85: 12 | H85: no | J85: 100 | K85: 80010228 | L85: 26B112 | M85: Ilaria Colleoni | N85: Annalisa Surini
A86: PartnersPol_ SE | B86: 30000 | D86: 46113 | G86: 12 | H86: no | J86: 100 | L86: 26B126 | M86: Lisa Pezzali | N86: Cristian Pellegrini
A87: PONTIGGIA MACCHINE ROTANTI_SE 26 | B87: 24000 | D87: 46054 | G87: 12 | H87: no | J87: 100 | L87: 26B114 | M87: Ilaria Colleoni | N87: Cristian Pellegrini
A88: Promos_Export su misura | B88: 39150 | D88: 46082 | G88: 7 | H88: no | J88: 100 | L88: 26B122 | M88: Valentina Bucca | N88: Valentina Bucca
A89: PROMOS_FESTIVAL DEL LEGNO | D89: 46174 | G89: 2 | H89: no | J89: 100 | M89: Gaia Seghezzi | N89: Annalisa Surini
A90: Promos_Inbuyer 2026 | B90: 2580 | D90: 46023 | G90: 12 | H90: no | J90: 100 | L90: 26B128 | M90: Lisa Pezzali | N90: Annalisa Surini
A91: RED V_sales expander | B91: 42670.5 | D91: 46023 | G91: 12 | H91: no | J91: 100 | L91: 25B210 | M91: Silvia Cortinovis | N91: Francesca Gritti | O91: PM nuovo post Poletti / Capire chi subentra come supervisor
A92: SALES_sales expander | B92: 25500 | D92: 46082 | G92: 12 | H92: no | J92: 100 | L92: 26B103 | M92: Silvia Cortinovis | N92: Cristian Pellegrini
A93: SCAME PARRE_Affiancamento strategico 2025 | B93: 25000 | D93: 45658 | G93: 12 | H93: no | J93: 100 | L93: 25B151 | M93: Francesca Gritti | N93: Francesca Gritti
A94: SCAME PARRE_SE Atex | B94: 22400 | D94: 45839 | G94: 12 | H94: no | J94: 100 | L94: 25B181 | M94: Giulia Pizzati | N94: Francesca Gritti/Cristian Pellegrini
A95: SCAME PARRE_SE E-Mobility | B95: 22400 | D95: 45839 | G95: 12 | H95: no | J95: 100 | L95: 25B181 | M95: Giulia Pizzati | N95: Francesca Gritti/Cristian Pellegrini
A96: Servitly_sales expander | B96: 20145 | D96: 46174 | G96: 6 | H96: no | J96: 100 | L96: 26B148 | M96: Silvia Cortinovis | N96: Francesca Gritti
A97: SOLDINI CARRELLI_MKTG 2026 | B97: 30000 | D97: 46023 | G97: 12 | H97: no | J97: 100 | L97: 25X121 | M97: Francesca Gritti | N97: Francesca Gritti
A98: UnioncoopServizi_SE | B98: 36178 | D98: 45931 | G98: 12 | H98: no | J98: 100 | L98: 25B209 | M98: Ilaria Colleoni | N98: Cristian Pellegrini
A99: UTILITA'_Customer Value Program | B99: 10700 | D99: 46174 | G99: 4 | H99: no | J99: 100 | L99: 26B145 | M99: Cristian Pellegrini | N99: Francesca Gritti
A100: VARVEL_Ricerca agenti | B100: 9500 | D100: 46023 | G100: 6 | H100: no | J100: 100 | L100: 25B195 | M100: Lisa Pezzali | N100: OK NO | O100: Chiuso, manca solo incontro finale
...

Sheet Pivot
A1: Probability | B1: (più elementi)
A2: Business_Unit | B2: (più elementi)
A3: Archived | B3: no
A5: Project | B5: PM | C5: =+VLOOKUP(A5,OLD!A:N,14,0) -> Supervisor
A6: 110 Laude_sales expander | B6: Lisa Pezzali | C6: =+VLOOKUP(A6,OLD!A:N,14,0) -> Cristian Pellegrini
A7: AAB_ALDEGANI_SE 26-27 | B7: Giulia Pizzati | C7: Cristian Pellegrini
A8: AAB_CORNA IMPIANTI SE SETT '26 | B8: Lisa Pezzali | C8: Annalisa Surini
A9: AAB_CRIMAR_SE 26/27 | B9: Lisa Pezzali | C9: =+VLOOKUP(A9,OLD!A:N,14,0) -> Francesca Gritti
A10: AAB_DOMINO_SE 26 | B10: Silvia Cortinovis | C10: =+VLOOKUP(A10,OLD!A:N,14,0) -> OK NO
A11: AAB_FORMENTI_SE 26_2 | B11: Silvia Cortinovis | C11: Annalisa Surini
A12: AAB_FRATUS_DEM 26 | B12: Ilaria Colleoni | C12: Gaia Seghezzi
A13: AAB_FRATUS_SE 2026 | B13: Ilaria Colleoni | C13: =+VLOOKUP(A13,OLD!A:N,14,0) -> Gaia Seghezzi
A14: AAB_GRAFFIDEA_SE 2026 | B14: Lisa Pezzali | C14: =+VLOOKUP(A14,OLD!A:N,14,0) -> Cristian Pellegrini
A15: AAB_KITERM SE 2025-26 | B15: Lisa Pezzali | C15: =+VLOOKUP(A15,OLD!A:N,14,0) -> Cristian Pellegrini
A16: AAB_KITERM SE 26/27 | B16: Lisa Pezzali | C16: Cristian Pellegrini
A17: AAB_ML ENGRAVING_ SE 26 | B17: Silvia Cortinovis | C17: =+VLOOKUP(A17,OLD!A:N,14,0) -> Annalisa Surini
A18: AAB_OFFICINE GAITI_SE 26/27 | B18: Lisa Pezzali | C18: =+VLOOKUP(A18,OLD!A:N,14,0) -> Annalisa Surini
A19: AAB_OMCS PLAST_SE 26 | B19: Chiara Ballabio | C19: =+VLOOKUP(A19,OLD!A:N,14,0) -> Cristian Pellegrini
A20: AAB_Plastic technology_SE | B20: Lisa Pezzali | C20: =+VLOOKUP(A20,OLD!A:N,14,0) -> Annalisa Surini
A21: AAB_VALMATECH_SE 26-27 | B21: Giulia Pizzati | C21: Annalisa Surini
A22: AAB_VERDELLI_SE 26 | B22: Annalisa Surini | C22: =+VLOOKUP(A22,OLD!A:N,14,0) -> Annalisa Surini
A23: AMBROSETTI_SE 26-27 | B23: Giulia Pizzati | C23: Cristian Pellegrini
A24: ANIMA DESK EUROPA | B24: Valentina Bucca
A25: APA MONZA_TEKNOFLUOR_SE25-26 | B25: Ilaria Colleoni | C25: =+VLOOKUP(A25,OLD!A:N,14,0) -> Cristian Pellegrini
A26: Barbiflex_SE 2026 | B26: Chiara Ballabio | C26: =+VLOOKUP(A26,OLD!A:N,14,0) -> Annalisa Surini
A27: BCM srl_sales expander | B27: Chiara Ballabio | C27: =+VLOOKUP(A27,OLD!A:N,14,0) -> Cristian Pellegrini
A28: BERTOLONI E BOTTURI _SE 25 | B28: FRANCESCA BOSIS | C28: =+VLOOKUP(A28,OLD!A:N,14,0) -> Gaia Seghezzi
A29: BOSCAROL_M&A | B29: Silvia Cortinovis | C29: =+VLOOKUP(A29,OLD!A:N,14,0) -> OK NO
A30: BOSCAROL_SE 26 | B30: Silvia Cortinovis | C30: =+VLOOKUP(A30,OLD!A:N,14,0) -> OK NO
A31: CE_DRILLING_SE 26 | B31: Chiara Ballabio | C31: =+VLOOKUP(A31,OLD!A:N,14,0) -> Annalisa Surini
A32: CEEVER_SE | B32: Chiara Ballabio | C32: =+VLOOKUP(A32,OLD!A:N,14,0) -> Cristian Pellegrini
A33: CERCoop_SE | B33: Ilaria Colleoni | C33: =+VLOOKUP(A33,OLD!A:N,14,0) -> Cristian Pellegrini
A34: CFG Serramenti_Affiancamento commerciale | B34: Annalisa Surini | C34: =+VLOOKUP(A34,OLD!A:N,14,0) -> Annalisa Surini
A35: CFG Serramenti_Formazione | B35: Annalisa Surini | C35: =+VLOOKUP(A35,OLD!A:N,14,0) -> Annalisa Surini
A36: CHEZ MOI ITALIA_ SE 27 | B36: Gaia Seghezzi
A37: CICLOTTE 2026 | B37: Bonfanti Luca
A38: CMA TEC_Fiera BIMU | B38: Chiara Ballabio | C38: Cristian Pellegrini
A39: CMA TEC_SE 2026 | B39: Chiara Ballabio | C39: =+VLOOKUP(A39,OLD!A:N,14,0) -> Cristian Pellegrini
A40: COLORICHIARI_SE 26 | B40: Giulia Pizzati | C40: Cristian Pellegrini
A41: COMINTEC_SE 26 | B41: Annalisa Surini | C41: =+VLOOKUP(A41,OLD!A:N,14,0) -> Annalisa Surini
A42: ComoNExT_sales expander | B42: Silvia Cortinovis | C42: =+VLOOKUP(A42,OLD!A:N,14,0) -> OK NO
A43: COMPUTES GROUP_SE 2026-2027 | B43: Chiara Ballabio
A44: CONF BARI_INCOMING MODA 2026 | B44: Ilaria Colleoni | C44: =+VLOOKUP(A44,OLD!A:N,14,0) -> Annalisa Surini
A45: Confcooperative Bergamo_Promozione filiera manifatturiera | B45: Cristian Pellegrini | C45: =+VLOOKUP(A45,OLD!A:N,14,0) -> Cristian Pellegrini
A46: E.D. Elettronica dedicata_affiancamento marketing 2026 | B46: Valentina Bucca
A47: E.D. Elettronica Dedicata_SE | B47: Chiara Ballabio | C47: =+VLOOKUP(A47,OLD!A:N,14,0) -> Valentina Bucca?
A48: ELETTROARMATURE_2026 | B48: Giulia Pizzati | C48: =+VLOOKUP(A48,OLD!A:N,14,0) -> OK NO
A49: ENNISWORK_SE 26 | B49: Ilaria Colleoni | C49: =+VLOOKUP(A49,OLD!A:N,14,0) -> Cristian Pellegrini
A50: Eurgomma_sales Expander 26 | B50: Giulia Pizzati | C50: =+VLOOKUP(A50,OLD!A:N,14,0) -> Cristian Pellegrini
A51: FARETE 2026_Incoming buyer | B51: Chiara Ballabio | C51: =+VLOOKUP(A51,OLD!A:N,14,0) -> Annalisa Surini
A52: FERIE 2026 | B52: Chiara Moioli
A53: FESTIVITÀ 2026 | B53: Chiara Moioli
A54: Forelli Pietro_sales Expander | B54: Chiara Ballabio | C54: =+VLOOKUP(A54,OLD!A:N,14,0) -> Cristian Pellegrini
A55: Frantoio Perilli_SE 26/27 | B55: Chiara Ballabio
A56: Gallazzini_formazione | B56: Annalisa Surini | C56: =+VLOOKUP(A56,OLD!A:N,14,0) -> Annalisa Surini
A57: GATTI PRECORVI_acquisto immagini per sito | B57: Federica Riganti
A58: Gentili Technology Equipment_profilazione | B58: Silvia Cortinovis | C58: Cristian Pellegrini
A59: GITRE srl_sales Expander | B59: Silvia Cortinovis | C59: =+VLOOKUP(A59,OLD!A:N,14,0) -> Cristian Pellegrini
A60: Glass to Power_2026 | B60: Francesca Gritti | C60: Francesca Gritti
A61: Glass to Power_Affiancamento strategico di mercato | B61: Francesca Gritti | C61: =+VLOOKUP(A61,OLD!A:N,14,0) -> Francesca Gritti
A62: Glass to Power_Consulenza e affiancamento 2026 | B62: Francesca Gritti | C62: =+VLOOKUP(A62,OLD!A:N,14,0) -> Francesca Gritti
A63: Grizzly Spa_ SE 26 | B63: Giulia Pizzati | C63: =+VLOOKUP(A63,OLD!A:N,14,0) -> Francesca Gritti
A64: HR Amministrazione 2026 | B64: Chiara Moioli | C64: =+VLOOKUP(A64,OLD!A:N,14,0) -> #N/A
A65: HR Formazione 2026 | B65: Chiara Moioli | C65: =+VLOOKUP(A65,OLD!A:N,14,0) -> #N/A
A66: HR selezione 2026 | B66: Chiara Moioli | C66: =+VLOOKUP(A66,OLD!A:N,14,0) -> #N/A
A67: IMO spa_sales Expander | B67: Ilaria Colleoni | C67: =+VLOOKUP(A67,OLD!A:N,14,0) -> #N/A
A68: Imolafilo_Sales Expander | B68: Chiara Ballabio | C68: =+VLOOKUP(A68,OLD!A:N,14,0) -> Cristian Pellegrini
A69: KOBAK_ricerca distributori Spagna | B69: Giulia Pizzati | C69: =+VLOOKUP(A69,OLD!A:N,14,0) -> #N/A
A70: Kopernicana_sales expander | B70: Francesca Gritti | C70: =+VLOOKUP(A70,OLD!A:N,14,0) -> Francesca Gritti
A71: KSENIA SECURITY_Ricerca distributori | B71: Ilaria Colleoni | C71: =+VLOOKUP(A71,OLD!A:N,14,0) -> Cristian Pellegrini
A72: Lovato_Analisi sales & mktg | B72: Valentina Bucca | C72: =+VLOOKUP(A72,OLD!A:N,14,0) -> Francesca Gritti
... A108: N-and_analisi strategica + sviluppo commerciale 2026 | B108: Giulia Pizzati | C108: =+VLOOKUP(A108,OLD!A:N,14,0) -> Francesca Gritti
A109: NILMA CONTRACT_SE 26-27 | B109: Giulia Pizzati | C109: Francesca Gritti
A110: OTIM_SE 2026 | B110: Annalisa Surini | C110: =+VLOOKUP(A110,OLD!A:N,14,0) -> Annalisa Surini
A111: Papermon_SE 26 | B111: Silvia Cortinovis | C111: =+VLOOKUP(A111,OLD!A:N,14,0) -> OK NO
A112: Parkair_sales Expander 2026 | B112: Silvia Cortinovis | C112: =+VLOOKUP(A112,OLD!A:N,14,0) -> Cristian Pellegrini
A113: PARTEC Srl_SE | B113: Ilaria Colleoni | C113: =+VLOOKUP(A113,OLD!A:N,14,0) -> Annalisa Surini
A114: PartnersPol_ SE | B114: Lisa Pezzali | C114: =+VLOOKUP(A114,OLD!A:N,14,0) -> Cristian Pellegrini
A115: Polypool 2026_affiancamento | B115: Cristian Pellegrini
A116: PONTIGGIA MACCHINE ROTANTI_SE 26 | B116: Ilaria Colleoni | C116: =+VLOOKUP(A116,OLD!A:N,14,0) -> Cristian Pellegrini
A117: Promos_Export su misura | B117: Valentina Bucca | C117: =+VLOOKUP(A117,OLD!A:N,14,0) -> Valentina Bucca
A118: PROMOS_FESTIVAL DEL LEGNO | B118: Lisa Pezzali | C118: =+VLOOKUP(A118,OLD!A:N,14,0) -> Annalisa Surini
A119: Promos_Inbuyer 2026 | B119: Lisa Pezzali | C119: =+VLOOKUP(A119,OLD!A:N,14,0) -> Annalisa Surini
A120: Promos_Webinar 17/09/26 | B120: Annalisa Surini | C120: Annalisa Surini
A121: REDV_sales expander | B121: Silvia Cortinovis | C121: Francesca Gritti
A122: SALES_sales expander | B122: Silvia Cortinovis | C122: =+VLOOKUP(A122,OLD!A:N,14,0) -> Cristian Pellegrini
A123: SCAME PARRE_Affiancamento strategico 2026 | B123: Francesca Gritti | C123: Francesca Gritti
A124: SCAME_BE_Governance & Leadership Assessment | B124: Chiara Moioli | C124: =+VLOOKUP(A124,OLD!A:N,14,0) -> #N/A
A125: Servitly_sales expander | B125: Silvia Cortinovis | C125: =+VLOOKUP(A125,OLD!A:N,14,0) -> Francesca Gritti
A126: SOLDINI CARRELLI_MKTG 2026 | B126: Francesca Gritti | C126: =+VLOOKUP(A126,OLD!A:N,14,0) -> Francesca Gritti
A127: TEKNOFLUOR_nov26-giu27 con pre fiera Achema | B127: Ilaria Colleoni | C127: Cristian Pellegrini
A128: Test per budget | B128: Annalisa Surini
A129: TrentinoSviluppo_attraction | B129: Francesca Gelmini | C129: Francesca Gritti
A130: UnioncoopServizi_SE | B130: Ilaria Colleoni | C130: =+VLOOKUP(A130,OLD!A:N,14,0) -> Cristian Pellegrini
A131: UTILITA'_Customer Value Program | B131: Francesca Gritti | C131: =+VLOOKUP(A131,OLD!A:N,14,0) -> Francesca Gritti
A132: Vetroasfalto Spa_SE | B132: Giulia Pizzati | C132: Annalisa Surini
A133: YSEdu_sales expander | B133: Francesca Gritti | C133: =+VLOOKUP(A133,OLD!A:N,14,0) -> Francesca Gritti
C134: =+VLOOKUP(A134,OLD!A:N,14,0) -> #N/A
C135: =+VLOOKUP(A135,OLD!A:N,14,0) -> #N/A
C136: =+VLOOKUP(A136,OLD!A:N,14,0) -> #N/A
...

Sheet Supervisor
A1: Project | B1: PM | C1: Supervisor | D1: Note
A2: 110 Laude_sales expander | B2: Lisa Pezzali | C2: Cristian Pellegrini
A3: AAB_ALDEGANI_SE 26-27 | B3: Giulia Pizzati | C3: Cristian Pellegrini
A4: AAB_CORNA IMPIANTI SE SETT '26 | B4: Lisa Pezzali | C4: Annalisa Surini
A5: AAB_CRIMAR_SE 26/27 | B5: Lisa Pezzali | C5: Francesca Gritti
A6: AAB_DOMINO_SE 26 | B6: Silvia Cortinovis | C6: Francesca Gritti | D6: Vede Franci Gritti negli allineamenti con Silvia
A7: AAB_FORMENTI_SE 26_2 | B7: Silvia Cortinovis | C7: Annalisa Surini
A8: AAB_FRATUS_DEM 26 | B8: Ilaria Colleoni | C8: Gaia Seghezzi
A9: AAB_FRATUS_SE 2026 | B9: Ilaria Colleoni | C9: Gaia Seghezzi
A10: AAB_GRAFFIDEA_SE 2026 | B10: Lisa Pezzali | C10: Cristian Pellegrini
A11: AAB_KITERM SE 2025-26 | B11: Lisa Pezzali | C11: Cristian Pellegrini
A12: AAB_KITERM SE 26/27 | B12: Lisa Pezzali | C12: Cristian Pellegrini
A13: AAB_ML ENGRAVING_ SE 26 | B13: Silvia Cortinovis | C13: Annalisa Surini
A14: AAB_OFFICINE GAITI_SE 26/27 | B14: Lisa Pezzali | C14: Annalisa Surini
A15: AAB_OMCS PLAST_SE 26 | B15: Chiara Ballabio | C15: Cristian Pellegrini
A16: AAB_Plastic technology_SE | B16: Lisa Pezzali | C16: Annalisa Surini
A17: AAB_VALMATECH_SE 26-27 | B17: Giulia Pizzati | C17: Annalisa Surini
A18: AAB_VERDELLI_SE 26 | B18: Annalisa Surini | C18: Annalisa Surini
... A23: BCM srl_sales expander | B23: Chiara Ballabio | C23: Cristian Pellegrini
A24: BERTOLONI E BOTTURI _SE 25 | B24: FRANCESCA BOSIS | C24: Gaia Seghezzi | D24: In gestione a Gaia Seghezzi in chiusura
A25: BOSCAROL_M&A | B25: Silvia Cortinovis | C25: Francesca Gritti | D25: Segue Franci Gritti negli allineamenti con Silvia
A26: BOSCAROL_SE 26 | B26: Silvia Cortinovis | C26: Francesca Gritti | D26: Segue Franci Gritti negli allineamenti con Silvia
A27: CE_DRILLING_SE 26 | B27: Chiara Ballabio | C27: Annalisa Surini
A28: CEEVER_SE | B28: Chiara Ballabio | C28: Cristian Pellegrini
A29: CERCoop_SE | B29: Ilaria Colleoni | C29: Cristian Pellegrini
A30: CFG Serramenti_Affiancamento commerciale | B30: Annalisa Surini | C30: Annalisa Surini
A31: CFG Serramenti_Formazione | B31: Annalisa Surini | C31: Annalisa Surini
A32: CHEZ MOI ITALIA_ SE 27 | B32: Gaia Seghezzi | D32: Parte a Novembre
A33: CMA TEC_Fiera BIMU | B33: Chiara Ballabio | C33: Cristian Pellegrini
A34: CMA TEC_SE 2026 | B34: Chiara Ballabio | C34: Cristian Pellegrini
A35: COLORICHIARI_SE 26 | B35: Giulia Pizzati | C35: Cristian Pellegrini
A36: COMINTEC_SE 26 | B36: Annalisa Surini | C36: Annalisa Surini
A37: ComoNExT_sales expander | B37: Silvia Cortinovis | C37: Francesca Gritti | D37: Presidio di Franci Gelmini + segue Franci Gritti negli allineamenti con Silvia
A38: COMPUTES GROUP_SE 2026-2027 | B38: Chiara Ballabio | C38: Cristian Pellegrini
A39: CONF BARI_INCOMING MODA 2026 | B39: Ilaria Colleoni | C39: Annalisa Surini
A40: Confcooperative Bergamo_Promozione filiera manifatturiera | B40: Cristian Pellegrini | C40: Cristian Pellegrini
A41: E.D. Elettronica dedicata_affiancamento marketing 2026 | B41: Valentina Bucca | C41: Valentina Bucca
A42: E.D. Elettronica Dedicata_SE | B42: Chiara Ballabio | C42: Valentina Bucca? | D42: Possiamo liberare Cristina Pellegrini?
A43: ELETTROARMATURE_2026 | B43: Giulia Pizzati | C43: Francesca Gritti | D43: Solo gestione + segue Franci Gritti negli allineamenti con Giulia
A44: ENNISWORK_SE 26 | B44: Ilaria Colleoni | C44: Cristian Pellegrini
A45: Eurgomma_sales Expander 26 | B45: Giulia Pizzati | C45: Cristian Pellegrini
A46: FARETE 2026_Incoming buyer | B46: Chiara Ballabio | C46: Annalisa Surini
A47: Forelli Pietro_sales Expander | B47: Chiara Ballabio | C47: Cristian Pellegrini
A48: Frantoio Perilli_SE 26/27 | B48: Chiara Ballabio | C48: Annalisa Surini
A49: Gallazzini_formazione | B49: Annalisa Surini | C49: Annalisa Surini
A50: Gentili Technology Equipment_profilazione | B50: Silvia Cortinovis | C50: Cristian Pellegrini
A51: GITRE srl_sales Expander | B51: Silvia Cortinovis | C51: Cristian Pellegrini
A52: Glass to Power_2026 | B52: Francesca Gritti | C52: Francesca Gritti
A53: Glass to Power_Affiancamento strategico di mercato | B53: Francesca Gritti | C53: Francesca Gritti
A54: Glass to Power_Consulenza e affiancamento 2026 | B54: Francesca Gritti | C54: Francesca Gritti
A55: Grizzly Spa_ SE 26 | B55: Giulia Pizzati | C55: Francesca Gritti
... A57: Imolafilo_Sales Expander | B57: Chiara Ballabio | C57: Cristian Pellegrini
A58: KOBAK_ricerca distributori Spagna | B58: Giulia Pizzati
A59: Kopernicana_sales expander | B59: Francesca Gritti | C59: Francesca Gritti
A60: KSENIA SECURITY_Ricerca distributori | B60: Ilaria Colleoni | C60: Cristian Pellegrini
A61: Lovato_Analisi sales & mktg | B61: Valentina Bucca | C61: Francesca Gritti
A62: Materia Prima_affiancamento luglio dicembre 2026 | B62: Silvia Cortinovis | C62: Cristian Pellegrini
A63: METANO NORD_Customer Value Program | B63: Francesca Gritti | C63: Francesca Gritti
A64: MINONZIO_2026 | B64: Giulia Pizzati | C64: Francesca Gritti | D64: Solo gestione + segue Franci Gritti negli allineamenti con Giulia
A65: MORESCHI_Affiancamento commerciale 2026 | B65: Annalisa Surini | C65: Annalisa Surini
A66: MY PLANT & GARDEN 2027_Promo visitatori | B66: Chiara Ballabio | C66: Annalisa Surini
A67: MY PLANT & GARDEN 2027_scouting buyer | B67: Chiara Ballabio | C67: Annalisa Surini
A68: MY PLANT & GARDEN 2027_scouting buyer 2 | B68: Chiara Ballabio | C68: Annalisa Surini
A69: MY PLANT & GARDEN 2027_vendita spazi | B69: Chiara Ballabio | C69: Annalisa Surini
A70: MY PLANT & GARDEN 2027_vendita spazi 2 | B70: Chiara Ballabio | C70: Annalisa Surini
A71: N-and_analisi strategica + sviluppo commerciale 2026 | B71: Giulia Pizzati | C71: Francesca Gritti | D71: Segue Franci Gritti negli allineamenti con Giulia
A72: NILMA CONTRACT_SE 26-27 | B72: Giulia Pizzati | C72: Francesca Gritti
A73: OTIM_SE 2026 | B73: Annalisa Surini | C73: Annalisa Surini
A74: Papermon_SE 26 | B74: Silvia Cortinovis | C74: Francesca Gritti | D74: Segue Franci Gritti negli allineamenti con Silvia
A75: Parkair_sales Expander 2026 | B75: Silvia Cortinovis | C75: Cristian Pellegrini
A76: PARTEC Srl_SE | B76: Ilaria Colleoni | C76: Annalisa Surini
A77: PartnersPol_ SE | B77: Lisa Pezzali | C77: Cristian Pellegrini
A78: Polypool 2026_affiancamento | B78: Cristian Pellegrini | C78: Cristian Pellegrini
A79: PONTIGGIA MACCHINE ROTANTI_SE 26 | B79: Ilaria Colleoni | C79: Cristian Pellegrini
A80: Promos_Export su misura | B80: Valentina Bucca | C80: Valentina Bucca
A81: PROMOS_FESTIVAL DEL LEGNO | B81: Lisa Pezzali | C81: Annalisa Surini
A82: Promos_Inbuyer 2026 | B82: Lisa Pezzali | C82: Annalisa Surini
A83: Promos_Webinar 17/09/26 | B83: Annalisa Surini | C83: Annalisa Surini
A84: REDV_sales expander | B84: Silvia Cortinovis | C84: Francesca Gritti
A85: SALES_sales expander | B85: Silvia Cortinovis | C85: Cristian Pellegrini
A86: SCAME PARRE_Affiancamento strategico 2026 | B86: Francesca Gritti | C86: Francesca Gritti
... A94: YSEdu_sales expander | B94: Francesca Gritti | C94: Francesca Gritti
